{
"meta":{"test_sets":[],"test_metrics":[],"learn_metrics":[{"best_value":"Min","name":"RMSE"}],"launch_mode":"Train","parameters":"","iteration_count":1000,"learn_sets":["learn"],"name":"experiment"},
"iterations":[
{"learn":[14.61268541],"iteration":0,"passed_time":0.06031201771,"remaining_time":60.25170569},
{"learn":[14.23196558],"iteration":1,"passed_time":0.06065767516,"remaining_time":30.26817991},
{"learn":[13.86674177],"iteration":2,"passed_time":0.06095141734,"remaining_time":20.25618769},
{"learn":[13.49946468],"iteration":3,"passed_time":0.06124724278,"remaining_time":15.25056345},
{"learn":[13.16661202],"iteration":4,"passed_time":0.06151765225,"remaining_time":12.2420128},
{"learn":[12.85632158],"iteration":5,"passed_time":0.06192939127,"remaining_time":10.25963582},
{"learn":[12.56784336],"iteration":6,"passed_time":0.06221180041,"remaining_time":8.825188259},
{"learn":[12.31617801],"iteration":7,"passed_time":0.06255841618,"remaining_time":7.757243606},
{"learn":[12.01509946],"iteration":8,"passed_time":0.06300944582,"remaining_time":6.93804009},
{"learn":[11.71512571],"iteration":9,"passed_time":0.06329252161,"remaining_time":6.26595964},
{"learn":[11.43264457],"iteration":10,"passed_time":0.06363397085,"remaining_time":5.72127247},
{"learn":[11.17973129],"iteration":11,"passed_time":0.06396917025,"remaining_time":5.266795017},
{"learn":[10.93746433],"iteration":12,"passed_time":0.06429966144,"remaining_time":4.881828142},
{"learn":[10.69387075],"iteration":13,"passed_time":0.06467615141,"remaining_time":4.555048949},
{"learn":[10.4615922],"iteration":14,"passed_time":0.06499651787,"remaining_time":4.268104673},
{"learn":[10.2299235],"iteration":15,"passed_time":0.06534246698,"remaining_time":4.018561719},
{"learn":[10.01419731],"iteration":16,"passed_time":0.06566995825,"remaining_time":3.797268763},
{"learn":[9.795856918],"iteration":17,"passed_time":0.06598678314,"remaining_time":3.599945614},
{"learn":[9.60040151],"iteration":18,"passed_time":0.06629352497,"remaining_time":3.422839368},
{"learn":[9.418664989],"iteration":19,"passed_time":0.06657518413,"remaining_time":3.262184022},
{"learn":[9.249278645],"iteration":20,"passed_time":0.06691521674,"remaining_time":3.119523675},
{"learn":[9.090113396],"iteration":21,"passed_time":0.06721991695,"remaining_time":2.988230853},
{"learn":[8.909548708],"iteration":22,"passed_time":0.06749278468,"remaining_time":2.866976114},
{"learn":[8.740140208],"iteration":23,"passed_time":0.06777869372,"remaining_time":2.756333545},
{"learn":[8.59377682],"iteration":24,"passed_time":0.06810768496,"remaining_time":2.656199713},
{"learn":[8.453885414],"iteration":25,"passed_time":0.06839913552,"remaining_time":2.562336846},
{"learn":[8.317732234],"iteration":26,"passed_time":0.0686925027,"remaining_time":2.475474264},
{"learn":[8.180896085],"iteration":27,"passed_time":0.06900224445,"remaining_time":2.395363629},
{"learn":[8.053220863],"iteration":28,"passed_time":0.06924732125,"remaining_time":2.318591343},
{"learn":[7.924234474],"iteration":29,"passed_time":0.06952164728,"remaining_time":2.247866595},
{"learn":[7.818879511],"iteration":30,"passed_time":0.0697783071,"remaining_time":2.181134825},
{"learn":[7.719346395],"iteration":31,"passed_time":0.07005809131,"remaining_time":2.119257262},
{"learn":[7.624163594],"iteration":32,"passed_time":0.07034208374,"remaining_time":2.061236212},
{"learn":[7.524952543],"iteration":33,"passed_time":0.07066120024,"remaining_time":2.007609395},
{"learn":[7.424464745],"iteration":34,"passed_time":0.07092681816,"remaining_time":1.955553701},
{"learn":[7.327482321],"iteration":35,"passed_time":0.07120481075,"remaining_time":1.906706599},
{"learn":[7.238666841],"iteration":36,"passed_time":0.07150192783,"remaining_time":1.860982608},
{"learn":[7.158842395],"iteration":37,"passed_time":0.07176379586,"remaining_time":1.816757148},
{"learn":[7.074348246],"iteration":38,"passed_time":0.07215316048,"remaining_time":1.777927877},
{"learn":[6.992269093],"iteration":39,"passed_time":0.07247977678,"remaining_time":1.739514643},
{"learn":[6.925219745],"iteration":40,"passed_time":0.07287305796,"remaining_time":1.7045186},
{"learn":[6.86013671],"iteration":41,"passed_time":0.07314025917,"remaining_time":1.668294483},
{"learn":[6.786739622],"iteration":42,"passed_time":0.0734030855,"remaining_time":1.633645415},
{"learn":[6.73057926],"iteration":43,"passed_time":0.07365795371,"remaining_time":1.600386449},
{"learn":[6.666356486],"iteration":44,"passed_time":0.07403981853,"remaining_time":1.571289482},
{"learn":[6.606182832],"iteration":45,"passed_time":0.07437610124,"remaining_time":1.542495665},
{"learn":[6.547854615],"iteration":46,"passed_time":0.07467292666,"remaining_time":1.514112747},
{"learn":[6.49240675],"iteration":47,"passed_time":0.07493354472,"remaining_time":1.48618197},
{"learn":[6.431317261],"iteration":48,"passed_time":0.07528820193,"remaining_time":1.461205715},
{"learn":[6.377586395],"iteration":49,"passed_time":0.07559990196,"remaining_time":1.436398137},
{"learn":[6.327558015],"iteration":50,"passed_time":0.07590060228,"remaining_time":1.412346501},
{"learn":[6.282040317],"iteration":51,"passed_time":0.07628825861,"remaining_time":1.390793638},
{"learn":[6.237655841],"iteration":52,"passed_time":0.07659620874,"remaining_time":1.368615277},
{"learn":[6.192792003],"iteration":53,"passed_time":0.07688249278,"remaining_time":1.346867373},
{"learn":[6.150579347],"iteration":54,"passed_time":0.07718727632,"remaining_time":1.326217748},
{"learn":[6.115693845],"iteration":55,"passed_time":0.07747726859,"remaining_time":1.306045385},
{"learn":[6.078780782],"iteration":56,"passed_time":0.07778713534,"remaining_time":1.28689945},
{"learn":[6.045146957],"iteration":57,"passed_time":0.07808083584,"remaining_time":1.268140472},
{"learn":[6.008080327],"iteration":58,"passed_time":0.07850032466,"remaining_time":1.252013653},
{"learn":[5.977575734],"iteration":59,"passed_time":0.07876644257,"remaining_time":1.2340076},
{"learn":[5.948036502],"iteration":60,"passed_time":0.07901614425,"remaining_time":1.216330483},
{"learn":[5.914888282],"iteration":61,"passed_time":0.0793119697,"remaining_time":1.199913348},
{"learn":[5.884957796],"iteration":62,"passed_time":0.07955892145,"remaining_time":1.183281102},
{"learn":[5.849539885],"iteration":63,"passed_time":0.07986570494,"remaining_time":1.168035935},
{"learn":[5.821387627],"iteration":64,"passed_time":0.08012698965,"remaining_time":1.152595928},
{"learn":[5.797012279],"iteration":65,"passed_time":0.08038994097,"remaining_time":1.137639468},
{"learn":[5.768685095],"iteration":66,"passed_time":0.08062710132,"remaining_time":1.122762471},
{"learn":[5.755484587],"iteration":67,"passed_time":0.08072368208,"remaining_time":1.10638929},
{"learn":[5.731887055],"iteration":68,"passed_time":0.0809629257,"remaining_time":1.092412809},
{"learn":[5.707148487],"iteration":69,"passed_time":0.08132129115,"remaining_time":1.08041144},
{"learn":[5.685365039],"iteration":70,"passed_time":0.08159203394,"remaining_time":1.067591543},
{"learn":[5.663541834],"iteration":71,"passed_time":0.08186206841,"remaining_time":1.055111104},
{"learn":[5.638108797],"iteration":72,"passed_time":0.08212885296,"remaining_time":1.042923927},
{"learn":[5.619204893],"iteration":73,"passed_time":0.08239551252,"remaining_time":1.031057359},
{"learn":[5.598472793],"iteration":74,"passed_time":0.08275496128,"remaining_time":1.020644522},
{"learn":[5.577007075],"iteration":75,"passed_time":0.08307361945,"remaining_time":1.010000321},
{"learn":[5.562637084],"iteration":76,"passed_time":0.08338802774,"remaining_time":0.9995733715},
{"learn":[5.54729991],"iteration":77,"passed_time":0.08365002076,"remaining_time":0.9887861428},
{"learn":[5.530737623],"iteration":78,"passed_time":0.0840623431,"remaining_time":0.9800179494},
{"learn":[5.513704873],"iteration":79,"passed_time":0.08432658606,"remaining_time":0.9697557397},
{"learn":[5.501575529],"iteration":80,"passed_time":0.08457107955,"remaining_time":0.9595163223},
{"learn":[5.484080734],"iteration":81,"passed_time":0.08483673913,"remaining_time":0.9497576405},
{"learn":[5.472178894],"iteration":82,"passed_time":0.08507710773,"remaining_time":0.9399482866},
{"learn":[5.458923342],"iteration":83,"passed_time":0.08533643415,"remaining_time":0.9305734962},
{"learn":[5.451382371],"iteration":84,"passed_time":0.08546501406,"remaining_time":0.9200057396},
{"learn":[5.441410748],"iteration":85,"passed_time":0.08579650522,"remaining_time":0.9118372764},
{"learn":[5.434047468],"iteration":86,"passed_time":0.0859323766,"remaining_time":0.9017960901},
{"learn":[5.422107497],"iteration":87,"passed_time":0.08616787033,"remaining_time":0.8930124743},
{"learn":[5.40731265],"iteration":88,"passed_time":0.08640453069,"remaining_time":0.8844328928},
{"learn":[5.396360181],"iteration":89,"passed_time":0.08664989915,"remaining_time":0.876126758},
{"learn":[5.383793239],"iteration":90,"passed_time":0.08695493268,"remaining_time":0.8685937781},
{"learn":[5.369605034],"iteration":91,"passed_time":0.08727742409,"remaining_time":0.8613902291},
{"learn":[5.357467333],"iteration":92,"passed_time":0.08752545915,"remaining_time":0.8536085102},
{"learn":[5.341109968],"iteration":93,"passed_time":0.08780207678,"remaining_time":0.8462625698},
{"learn":[5.330529276],"iteration":94,"passed_time":0.08806540309,"remaining_time":0.83893884},
{"learn":[5.319862075],"iteration":95,"passed_time":0.08831118821,"remaining_time":0.8315970223},
{"learn":[5.313052243],"iteration":96,"passed_time":0.08855351508,"remaining_time":0.8243693208},
{"learn":[5.299677207],"iteration":97,"passed_time":0.08879625861,"remaining_time":0.817288013},
{"learn":[5.287546698],"iteration":98,"passed_time":0.0891207083,"remaining_time":0.8110884665},
{"learn":[5.279803754],"iteration":99,"passed_time":0.08935886862,"remaining_time":0.8042298176},
{"learn":[5.272254612],"iteration":100,"passed_time":0.08959569564,"remaining_time":0.7974903998},
{"learn":[5.268813888],"iteration":101,"passed_time":0.08969915122,"remaining_time":0.7897042921},
{"learn":[5.258113767],"iteration":102,"passed_time":0.09005489174,"remaining_time":0.7842644455},
{"learn":[5.251018576],"iteration":103,"passed_time":0.09039342438,"remaining_time":0.7787741178},
{"learn":[5.24171237],"iteration":104,"passed_time":0.09075528974,"remaining_time":0.773580803},
{"learn":[5.233984943],"iteration":105,"passed_time":0.09110382212,"remaining_time":0.7683661979},
{"learn":[5.226240449],"iteration":106,"passed_time":0.09136277355,"remaining_time":0.7624949232},
{"learn":[5.220541644],"iteration":107,"passed_time":0.09166009896,"remaining_time":0.757044521},
{"learn":[5.211712096],"iteration":108,"passed_time":0.09253932553,"remaining_time":0.7564453124},
{"learn":[5.203388597],"iteration":109,"passed_time":0.09280136021,"remaining_time":0.750847369},
{"learn":[5.196026544],"iteration":110,"passed_time":0.09305868669,"remaining_time":0.7453078601},
{"learn":[5.188716772],"iteration":111,"passed_time":0.09329638869,"remaining_time":0.7397070817},
{"learn":[5.182163132],"iteration":112,"passed_time":0.09357629789,"remaining_time":0.734532533},
{"learn":[5.17764747],"iteration":113,"passed_time":0.0938262079,"remaining_time":0.7292107035},
{"learn":[5.170548056],"iteration":114,"passed_time":0.09408195109,"remaining_time":0.7240219714},
{"learn":[5.165901827],"iteration":115,"passed_time":0.0942803208,"remaining_time":0.7184810654},
{"learn":[5.160333668],"iteration":116,"passed_time":0.09458864592,"remaining_time":0.7138613192},
{"learn":[5.148953243],"iteration":117,"passed_time":0.09484726402,"remaining_time":0.7089431091},
{"learn":[5.144729126],"iteration":118,"passed_time":0.09508688264,"remaining_time":0.7039625513},
{"learn":[5.139939946],"iteration":119,"passed_time":0.0953534172,"remaining_time":0.6992583928},
{"learn":[5.132898872],"iteration":120,"passed_time":0.0956624923,"remaining_time":0.6949366176},
{"learn":[5.129073077],"iteration":121,"passed_time":0.0958914862,"remaining_time":0.6901043023},
{"learn":[5.127123916],"iteration":122,"passed_time":0.09598202545,"remaining_time":0.6843596449},
{"learn":[5.121282057],"iteration":123,"passed_time":0.09627164273,"remaining_time":0.6801125728},
{"learn":[5.114489821],"iteration":124,"passed_time":0.09652971919,"remaining_time":0.6757080343},
{"learn":[5.107777291],"iteration":125,"passed_time":0.09679308717,"remaining_time":0.6714060173},
{"learn":[5.103518754],"iteration":126,"passed_time":0.09704924701,"remaining_time":0.6671180523},
{"learn":[5.101133351],"iteration":127,"passed_time":0.09718403508,"remaining_time":0.662066239},
{"learn":[5.096462705],"iteration":128,"passed_time":0.09749086024,"remaining_time":0.6582522424},
{"learn":[5.08562082],"iteration":129,"passed_time":0.09777322771,"remaining_time":0.6543285239},
{"learn":[5.080483682],"iteration":130,"passed_time":0.09826933949,"remaining_time":0.6518782902},
{"learn":[5.07437499],"iteration":131,"passed_time":0.09874145191,"remaining_time":0.6492998505},
{"learn":[5.070683732],"iteration":132,"passed_time":0.09911885852,"remaining_time":0.6461357168},
{"learn":[5.06432037],"iteration":133,"passed_time":0.09945364127,"remaining_time":0.6427377115},
{"learn":[5.057436484],"iteration":134,"passed_time":0.0997064262,"remaining_time":0.6388596938},
{"learn":[5.053254656],"iteration":135,"passed_time":0.09996725258,"remaining_time":0.6350860752},
{"learn":[5.04801663],"iteration":136,"passed_time":0.1002599531,"remaining_time":0.6315645222},
{"learn":[5.045680836],"iteration":137,"passed_time":0.1004673643,"remaining_time":0.6275570144},
{"learn":[5.041857933],"iteration":138,"passed_time":0.1007242324,"remaining_time":0.6239105331},
{"learn":[5.035264888],"iteration":139,"passed_time":0.1010148497,"remaining_time":0.6205197908},
{"learn":[5.028771948],"iteration":140,"passed_time":0.101302217,"remaining_time":0.6171532227},
{"learn":[5.024912247],"iteration":141,"passed_time":0.101615667,"remaining_time":0.6139876216},
{"learn":[5.02239068],"iteration":142,"passed_time":0.1019627411,"remaining_time":0.6110634202},
{"learn":[5.017110572],"iteration":143,"passed_time":0.1021932349,"remaining_time":0.6074820076},
{"learn":[5.010707886],"iteration":144,"passed_time":0.1025251844,"remaining_time":0.6045450529},
{"learn":[5.004389868],"iteration":145,"passed_time":0.1027855941,"remaining_time":0.6012253246},
{"learn":[4.997628683],"iteration":146,"passed_time":0.1030200046,"remaining_time":0.597796353},
{"learn":[4.991497851],"iteration":147,"passed_time":0.1032609565,"remaining_time":0.5944482089},
{"learn":[4.988345253],"iteration":148,"passed_time":0.1042578882,"remaining_time":0.5954594825},
{"learn":[4.98460423],"iteration":149,"passed_time":0.1045097149,"remaining_time":0.5922217175},
{"learn":[4.982441783],"iteration":150,"passed_time":0.1047862908,"remaining_time":0.589162655},
{"learn":[4.977461771],"iteration":151,"passed_time":0.1050502421,"remaining_time":0.5860697718},
{"learn":[4.973601586],"iteration":152,"passed_time":0.1052910274,"remaining_time":0.5828856221},
{"learn":[4.968328804],"iteration":153,"passed_time":0.1055189796,"remaining_time":0.5796691998},
{"learn":[4.9640736],"iteration":154,"passed_time":0.1057609315,"remaining_time":0.5765676589},
{"learn":[4.960865882],"iteration":155,"passed_time":0.1059872588,"remaining_time":0.5734182464},
{"learn":[4.957014156],"iteration":156,"passed_time":0.1062423353,"remaining_time":0.5704604376},
{"learn":[4.952244852],"iteration":157,"passed_time":0.106480579,"remaining_time":0.5674471362},
{"learn":[4.949695675],"iteration":158,"passed_time":0.1074725526,"remaining_time":0.568455451},
{"learn":[4.946584698],"iteration":159,"passed_time":0.1077981689,"remaining_time":0.5659403867},
{"learn":[4.940192834],"iteration":160,"passed_time":0.1081033691,"remaining_time":0.5633461283},
{"learn":[4.936727994],"iteration":161,"passed_time":0.108358279,"remaining_time":0.5605199862},
{"learn":[4.932342063],"iteration":162,"passed_time":0.1086422714,"remaining_time":0.557874731},
{"learn":[4.925830838],"iteration":163,"passed_time":0.108971471,"remaining_time":0.5554887178},
{"learn":[4.922571773],"iteration":164,"passed_time":0.1092062147,"remaining_time":0.552649632},
{"learn":[4.918395814],"iteration":165,"passed_time":0.1094659578,"remaining_time":0.5499675228},
{"learn":[4.911142452],"iteration":166,"passed_time":0.1097512418,"remaining_time":0.5474418231},
{"learn":[4.908276131],"iteration":167,"passed_time":0.1100131932,"remaining_time":0.5448272425},
{"learn":[4.904584645],"iteration":168,"passed_time":0.1102763112,"remaining_time":0.5422462402},
{"learn":[4.89795517],"iteration":169,"passed_time":0.1106235103,"remaining_time":0.5401030207},
{"learn":[4.895556491],"iteration":170,"passed_time":0.1108766285,"remaining_time":0.5375247078},
{"learn":[4.890591233],"iteration":171,"passed_time":0.111144913,"remaining_time":0.5350464418},
{"learn":[4.884629277],"iteration":172,"passed_time":0.111421489,"remaining_time":0.5326333607},
{"learn":[4.880550786],"iteration":173,"passed_time":0.1116894402,"remaining_time":0.5302038942},
{"learn":[4.876384842],"iteration":174,"passed_time":0.1119388502,"remaining_time":0.5277117224},
{"learn":[4.872638238],"iteration":175,"passed_time":0.1121925518,"remaining_time":0.5252651288},
{"learn":[4.869137118],"iteration":176,"passed_time":0.1124410452,"remaining_time":0.522819097},
{"learn":[4.863587157],"iteration":177,"passed_time":0.1127137046,"remaining_time":0.5205093548},
{"learn":[4.858028614],"iteration":178,"passed_time":0.1129770725,"remaining_time":0.5181797573},
{"learn":[4.853838176],"iteration":179,"passed_time":0.1132198161,"remaining_time":0.5157791621},
{"learn":[4.853462329],"iteration":180,"passed_time":0.1133272715,"remaining_time":0.5127902508},
{"learn":[4.851573196],"iteration":181,"passed_time":0.1135690568,"remaining_time":0.5104367496},
{"learn":[4.848442087],"iteration":182,"passed_time":0.1139711294,"remaining_time":0.5088219273},
{"learn":[4.845547104],"iteration":183,"passed_time":0.1142304558,"remaining_time":0.5065872388},
{"learn":[4.839868817],"iteration":184,"passed_time":0.1144759493,"remaining_time":0.5043129657},
{"learn":[4.836336958],"iteration":185,"passed_time":0.1147150679,"remaining_time":0.5020326089},
{"learn":[4.831124789],"iteration":186,"passed_time":0.1149736443,"remaining_time":0.4998586783},
{"learn":[4.827407333],"iteration":187,"passed_time":0.1152090964,"remaining_time":0.4976052461},
{"learn":[4.824088918],"iteration":188,"passed_time":0.1154395902,"remaining_time":0.4953518925},
{"learn":[4.820934539],"iteration":189,"passed_time":0.1156781672,"remaining_time":0.4931542918},
{"learn":[4.816975227],"iteration":190,"passed_time":0.1160188248,"remaining_time":0.4914095773},
{"learn":[4.812340486],"iteration":191,"passed_time":0.1162441938,"remaining_time":0.4891943156},
{"learn":[4.806402747],"iteration":192,"passed_time":0.1165162282,"remaining_time":0.4871947988},
{"learn":[4.801521788],"iteration":193,"passed_time":0.1168225951,"remaining_time":0.48535573},
{"learn":[4.797601172],"iteration":194,"passed_time":0.1170773799,"remaining_time":0.4833194402},
{"learn":[4.792694629],"iteration":195,"passed_time":0.1173424562,"remaining_time":0.4813435448},
{"learn":[4.789794613],"iteration":196,"passed_time":0.1176326985,"remaining_time":0.4794875983},
{"learn":[4.785367055],"iteration":197,"passed_time":0.1179349404,"remaining_time":0.4776960718},
{"learn":[4.780376856],"iteration":198,"passed_time":0.1181793089,"remaining_time":0.475686565},
{"learn":[4.776691261],"iteration":199,"passed_time":0.118437552,"remaining_time":0.4737502081},
{"learn":[4.773470753],"iteration":200,"passed_time":0.1186950452,"remaining_time":0.4718275676},
{"learn":[4.77207327],"iteration":201,"passed_time":0.1190124534,"remaining_time":0.4701581078},
{"learn":[4.767347177],"iteration":202,"passed_time":0.1193073205,"remaining_time":0.4684134702},
{"learn":[4.763983068],"iteration":203,"passed_time":0.1195550639,"remaining_time":0.4664991709},
{"learn":[4.761588849],"iteration":204,"passed_time":0.1198192235,"remaining_time":0.4646647937},
{"learn":[4.758558086],"iteration":205,"passed_time":0.1200804249,"remaining_time":0.4628342591},
{"learn":[4.753678804],"iteration":206,"passed_time":0.1203125854,"remaining_time":0.4609076339},
{"learn":[4.746510889],"iteration":207,"passed_time":0.1205506207,"remaining_time":0.4590196712},
{"learn":[4.744840601],"iteration":208,"passed_time":0.1207897393,"remaining_time":0.4571515972},
{"learn":[4.741702222],"iteration":209,"passed_time":0.1211341885,"remaining_time":0.4556952805},
{"learn":[4.739352853],"iteration":210,"passed_time":0.1214231808,"remaining_time":0.454042131},
{"learn":[4.735539287],"iteration":211,"passed_time":0.1216929653,"remaining_time":0.4523304558},
{"learn":[4.730726751],"iteration":212,"passed_time":0.1219437502,"remaining_time":0.4505621195},
{"learn":[4.726416092],"iteration":213,"passed_time":0.1222413673,"remaining_time":0.4489799753},
{"learn":[4.721293082],"iteration":214,"passed_time":0.1225862331,"remaining_time":0.447582293},
{"learn":[4.718443695],"iteration":215,"passed_time":0.1228736005,"remaining_time":0.445985661},
{"learn":[4.711627962],"iteration":216,"passed_time":0.1231254271,"remaining_time":0.4442728544},
{"learn":[4.709790764],"iteration":217,"passed_time":0.1233955449,"remaining_time":0.4426390647},
{"learn":[4.706913073],"iteration":218,"passed_time":0.1236364551,"remaining_time":0.4409135683},
{"learn":[4.703846389],"iteration":219,"passed_time":0.1238974482,"remaining_time":0.4392727708},
{"learn":[4.701001135],"iteration":220,"passed_time":0.1241352752,"remaining_time":0.4375628025},
{"learn":[4.700380864],"iteration":221,"passed_time":0.1244191843,"remaining_time":0.4360275917},
{"learn":[4.695837486],"iteration":222,"passed_time":0.1246489282,"remaining_time":0.4343148752},
{"learn":[4.691242996],"iteration":223,"passed_time":0.1249010464,"remaining_time":0.4326929109},
{"learn":[4.690284609],"iteration":224,"passed_time":0.1251571229,"remaining_time":0.4310967568},
{"learn":[4.68827119],"iteration":225,"passed_time":0.12539295,"remaining_time":0.4294431119},
{"learn":[4.686922425],"iteration":226,"passed_time":0.1256358602,"remaining_time":0.427826079},
{"learn":[4.686085874],"iteration":227,"passed_time":0.1258795204,"remaining_time":0.4262236391},
{"learn":[4.683230741],"iteration":228,"passed_time":0.1261233472,"remaining_time":0.4246336275},
{"learn":[4.6773487],"iteration":229,"passed_time":0.1263592576,"remaining_time":0.4230288188},
{"learn":[4.671462906],"iteration":230,"passed_time":0.1266729575,"remaining_time":0.421694824},
{"learn":[4.664799601],"iteration":231,"passed_time":0.1269526168,"remaining_time":0.4202569382},
{"learn":[4.660979386],"iteration":232,"passed_time":0.1271870688,"remaining_time":0.4186801794},
{"learn":[4.656281279],"iteration":233,"passed_time":0.1274475202,"remaining_time":0.4172000022},
{"learn":[4.651997094],"iteration":234,"passed_time":0.1276590563,"remaining_time":0.4155709704},
{"learn":[4.650151977],"iteration":235,"passed_time":0.1280033804,"remaining_time":0.4143838248},
{"learn":[4.648478046],"iteration":236,"passed_time":0.1282549154,"remaining_time":0.4129050652},
{"learn":[4.646364602],"iteration":237,"passed_time":0.1285733652,"remaining_time":0.4116508584},
{"learn":[4.642635873],"iteration":238,"passed_time":0.1288403581,"remaining_time":0.4102406382},
{"learn":[4.640860821],"iteration":239,"passed_time":0.1290809767,"remaining_time":0.4087564262},
{"learn":[4.639446822],"iteration":240,"passed_time":0.1293451363,"remaining_time":0.4073566742},
{"learn":[4.637120072],"iteration":241,"passed_time":0.1296650861,"remaining_time":0.4061410549},
{"learn":[4.633769267],"iteration":242,"passed_time":0.1299227876,"remaining_time":0.4047388898},
{"learn":[4.630491517],"iteration":243,"passed_time":0.130172156,"remaining_time":0.4033202865},
{"learn":[4.627813333],"iteration":244,"passed_time":0.130432899,"remaining_time":0.4019462806},
{"learn":[4.622496304],"iteration":245,"passed_time":0.1307140165,"remaining_time":0.4006437742},
{"learn":[4.618979301],"iteration":246,"passed_time":0.1310088837,"remaining_time":0.3993914551},
{"learn":[4.616563458],"iteration":247,"passed_time":0.131257627,"remaining_time":0.3980069981},
{"learn":[4.614759385],"iteration":248,"passed_time":0.131533703,"remaining_time":0.3967141002},
{"learn":[4.61251363],"iteration":249,"passed_time":0.1317508222,"remaining_time":0.3952524667},
{"learn":[4.608796693],"iteration":250,"passed_time":0.1321124793,"remaining_time":0.3942320596},
{"learn":[4.60847774],"iteration":251,"passed_time":0.1323833054,"remaining_time":0.3929472715},
{"learn":[4.605195659],"iteration":252,"passed_time":0.132620799,"remaining_time":0.3915720825},
{"learn":[4.60103766],"iteration":253,"passed_time":0.1329022499,"remaining_time":0.3903349544},
{"learn":[4.599325598],"iteration":254,"passed_time":0.1331827007,"remaining_time":0.3891024002},
{"learn":[4.597012808],"iteration":255,"passed_time":0.1334820678,"remaining_time":0.3879322594},
{"learn":[4.594161533],"iteration":256,"passed_time":0.1338236837,"remaining_time":0.3868910387},
{"learn":[4.592197259],"iteration":257,"passed_time":0.1340408445,"remaining_time":0.3854973126},
{"learn":[4.58952828],"iteration":258,"passed_time":0.1342550888,"remaining_time":0.3841043275},
{"learn":[4.585816572],"iteration":259,"passed_time":0.1345549142,"remaining_time":0.3829639865},
{"learn":[4.582934052],"iteration":260,"passed_time":0.1347758666,"remaining_time":0.3816067641},
{"learn":[4.582234842],"iteration":261,"passed_time":0.1350595257,"remaining_time":0.3804348472},
{"learn":[4.57571562],"iteration":262,"passed_time":0.1352923945,"remaining_time":0.3791273565},
{"learn":[4.571197349],"iteration":263,"passed_time":0.1355343464,"remaining_time":0.3778533293},
{"learn":[4.56723703],"iteration":264,"passed_time":0.1358270886,"remaining_time":0.3767279627},
{"learn":[4.560335567],"iteration":265,"passed_time":0.1361433718,"remaining_time":0.3756738155},
{"learn":[4.554709345],"iteration":266,"passed_time":0.1364163229,"remaining_time":0.3745062348},
{"learn":[4.552806306],"iteration":267,"passed_time":0.1367178982,"remaining_time":0.373423513},
{"learn":[4.550766241],"iteration":268,"passed_time":0.1371480951,"remaining_time":0.3726961245},
{"learn":[4.549216045],"iteration":269,"passed_time":0.137400505,"remaining_time":0.3714902543},
{"learn":[4.547687452],"iteration":270,"passed_time":0.1376366237,"remaining_time":0.3702475966},
{"learn":[4.545642435],"iteration":271,"passed_time":0.1378833671,"remaining_time":0.3690407767},
{"learn":[4.543930359],"iteration":272,"passed_time":0.1381197775,"remaining_time":0.3678134734},
{"learn":[4.541029943],"iteration":273,"passed_time":0.1383932285,"remaining_time":0.3666915472},
{"learn":[4.537781449],"iteration":274,"passed_time":0.1386493884,"remaining_time":0.3655302057},
{"learn":[4.53066128],"iteration":275,"passed_time":0.1389013817,"remaining_time":0.3643644939},
{"learn":[4.526763956],"iteration":276,"passed_time":0.1391522916,"remaining_time":0.3632025518},
{"learn":[4.522036004],"iteration":277,"passed_time":0.1394552419,"remaining_time":0.3621823189},
{"learn":[4.515307629],"iteration":278,"passed_time":0.1397102768,"remaining_time":0.3610434034},
{"learn":[4.51109143],"iteration":279,"passed_time":0.1400717671,"remaining_time":0.3601845441},
{"learn":[4.508233494],"iteration":280,"passed_time":0.1403228021,"remaining_time":0.3590466004},
{"learn":[4.502555629],"iteration":281,"passed_time":0.1405797953,"remaining_time":0.357930117},
{"learn":[4.500081355],"iteration":282,"passed_time":0.1408236638,"remaining_time":0.3567864556},
{"learn":[4.495281743],"iteration":283,"passed_time":0.1410721571,"remaining_time":0.3556607906},
{"learn":[4.492138869],"iteration":284,"passed_time":0.1413701909,"remaining_time":0.3546655666},
{"learn":[4.491708261],"iteration":285,"passed_time":0.1417405977,"remaining_time":0.3538558977},
{"learn":[4.489398865],"iteration":286,"passed_time":0.1421343788,"remaining_time":0.3531073593},
{"learn":[4.485796373],"iteration":287,"passed_time":0.1424025384,"remaining_time":0.3520507198},
{"learn":[4.479542205],"iteration":288,"passed_time":0.1426591982,"remaining_time":0.3509712454},
{"learn":[4.475986993],"iteration":289,"passed_time":0.1429251078,"remaining_time":0.3499200914},
{"learn":[4.468661855],"iteration":290,"passed_time":0.1431692679,"remaining_time":0.3488213435},
{"learn":[4.463785664],"iteration":291,"passed_time":0.1434310526,"remaining_time":0.3477711824},
{"learn":[4.460445831],"iteration":292,"passed_time":0.1436736712,"remaining_time":0.3466801553},
{"learn":[4.45692492],"iteration":293,"passed_time":0.144003954,"remaining_time":0.3458054134},
{"learn":[4.454031688],"iteration":294,"passed_time":0.144241531,"remaining_time":0.3447128114},
{"learn":[4.451672391],"iteration":295,"passed_time":0.1445258568,"remaining_time":0.3437371729},
{"learn":[4.45031553],"iteration":296,"passed_time":0.1447914747,"remaining_time":0.3427219081},
{"learn":[4.446782666],"iteration":297,"passed_time":0.1450771338,"remaining_time":0.3417588855},
{"learn":[4.444369689],"iteration":298,"passed_time":0.1453455016,"remaining_time":0.3407598549},
{"learn":[4.44411683],"iteration":299,"passed_time":0.1455906201,"remaining_time":0.3397114468},
{"learn":[4.440876943],"iteration":300,"passed_time":0.1458618628,"remaining_time":0.3387290436},
{"learn":[4.439336453],"iteration":301,"passed_time":0.1461691463,"remaining_time":0.3378346494},
{"learn":[4.436666901],"iteration":302,"passed_time":0.1464241395,"remaining_time":0.3368238457},
{"learn":[4.433043336],"iteration":303,"passed_time":0.1466579666,"remaining_time":0.3357695552},
{"learn":[4.431419305],"iteration":304,"passed_time":0.1469263761,"remaining_time":0.3347994473},
{"learn":[4.428859646],"iteration":305,"passed_time":0.147193994,"remaining_time":0.3338321302},
{"learn":[4.424552441],"iteration":306,"passed_time":0.1474388625,"remaining_time":0.3328180186},
{"learn":[4.422706391],"iteration":307,"passed_time":0.1477969779,"remaining_time":0.33206334},
{"learn":[4.421427994],"iteration":308,"passed_time":0.1481050947,"remaining_time":0.3311994189},
{"learn":[4.418733158],"iteration":309,"passed_time":0.1484451273,"remaining_time":0.3304101221},
{"learn":[4.415656941],"iteration":310,"passed_time":0.1492526891,"remaining_time":0.3306594946},
{"learn":[4.410747417],"iteration":311,"passed_time":0.1495409315,"remaining_time":0.3297569258},
{"learn":[4.408126521],"iteration":312,"passed_time":0.1498344236,"remaining_time":0.3288698052},
{"learn":[4.407843853],"iteration":313,"passed_time":0.1501330407,"remaining_time":0.3279976621},
{"learn":[4.405219398],"iteration":314,"passed_time":0.1503734926,"remaining_time":0.3270026744},
{"learn":[4.402708465],"iteration":315,"passed_time":0.151298093,"remaining_time":0.3274933405},
{"learn":[4.40104971],"iteration":316,"passed_time":0.1515551694,"remaining_time":0.3265368477},
{"learn":[4.400830038],"iteration":317,"passed_time":0.1517807468,"remaining_time":0.325517199},
{"learn":[4.39784288],"iteration":318,"passed_time":0.152022282,"remaining_time":0.3245365957},
{"learn":[4.393741845],"iteration":319,"passed_time":0.1523519399,"remaining_time":0.3237478722},
{"learn":[4.393425936],"iteration":320,"passed_time":0.1525996833,"remaining_time":0.3227887381},
{"learn":[4.390505974],"iteration":321,"passed_time":0.1528521765,"remaining_time":0.3218440239},
{"learn":[4.390305136],"iteration":322,"passed_time":0.1531290858,"remaining_time":0.3209547712},
{"learn":[4.38568203],"iteration":323,"passed_time":0.1534728267,"remaining_time":0.3202087371},
{"learn":[4.383057135],"iteration":324,"passed_time":0.1537577357,"remaining_time":0.3193429896},
{"learn":[4.380662684],"iteration":325,"passed_time":0.1540407699,"remaining_time":0.3184769291},
{"learn":[4.37805727],"iteration":326,"passed_time":0.1542888883,"remaining_time":0.3175425743},
{"learn":[4.373708319],"iteration":327,"passed_time":0.1545745056,"remaining_time":0.3166892311},
{"learn":[4.36887921],"iteration":328,"passed_time":0.1548514983,"remaining_time":0.3158217487},
{"learn":[4.367895929],"iteration":329,"passed_time":0.1552343631,"remaining_time":0.3151727977},
{"learn":[4.362140573],"iteration":330,"passed_time":0.1555263553,"remaining_time":0.3143417876},
{"learn":[4.361931924],"iteration":331,"passed_time":0.155885554,"remaining_time":0.3136492473},
{"learn":[4.359656377],"iteration":332,"passed_time":0.1561766296,"remaining_time":0.3128222581},
{"learn":[4.354281355],"iteration":333,"passed_time":0.1564388726,"remaining_time":0.3119409855},
{"learn":[4.348589447],"iteration":334,"passed_time":0.1566983241,"remaining_time":0.3110578671},
{"learn":[4.346355698],"iteration":335,"passed_time":0.1569244847,"remaining_time":0.3101126721},
{"learn":[4.343894047],"iteration":336,"passed_time":0.1572050189,"remaining_time":0.3092787167},
{"learn":[4.341561356],"iteration":337,"passed_time":0.1574575538,"remaining_time":0.3083931971},
{"learn":[4.338869061],"iteration":338,"passed_time":0.1577187969,"remaining_time":0.3075283915},
{"learn":[4.333720063],"iteration":339,"passed_time":0.1580233721,"remaining_time":0.3067512517},
{"learn":[4.330892223],"iteration":340,"passed_time":0.1582713655,"remaining_time":0.3058675362},
{"learn":[4.328311474],"iteration":341,"passed_time":0.1585309419,"remaining_time":0.3050098238},
{"learn":[4.324580133],"iteration":342,"passed_time":0.1588213925,"remaining_time":0.3042147372},
{"learn":[4.323354432],"iteration":343,"passed_time":0.1590904686,"remaining_time":0.3033818239},
{"learn":[4.323159553],"iteration":344,"passed_time":0.1594423759,"remaining_time":0.3027094383},
{"learn":[4.318639682],"iteration":345,"passed_time":0.1597614924,"remaining_time":0.301976925},
{"learn":[4.312712208],"iteration":346,"passed_time":0.1599963612,"remaining_time":0.3010882531},
{"learn":[4.311461062],"iteration":347,"passed_time":0.1602624791,"remaining_time":0.3002618861},
{"learn":[4.311178356],"iteration":348,"passed_time":0.1604963895,"remaining_time":0.299378652},
{"learn":[4.311102505],"iteration":349,"passed_time":0.1607870484,"remaining_time":0.2986045185},
{"learn":[4.310232308],"iteration":350,"passed_time":0.1610107508,"remaining_time":0.2977093369},
{"learn":[4.305128197],"iteration":351,"passed_time":0.1613467418,"remaining_time":0.2970246838},
{"learn":[4.304595496],"iteration":352,"passed_time":0.1616267344,"remaining_time":0.2962393687},
{"learn":[4.3004992],"iteration":353,"passed_time":0.1618948106,"remaining_time":0.2954351628},
{"learn":[4.297581524],"iteration":354,"passed_time":0.1621470122,"remaining_time":0.2946051348},
{"learn":[4.297355825],"iteration":355,"passed_time":0.1630242388,"remaining_time":0.2949090163},
{"learn":[4.295758715],"iteration":356,"passed_time":0.1633871458,"remaining_time":0.2942799293},
{"learn":[4.292500657],"iteration":357,"passed_time":0.1636611802,"remaining_time":0.2934929544},
{"learn":[4.290797586],"iteration":358,"passed_time":0.1639860465,"remaining_time":0.2927995984},
{"learn":[4.286410608],"iteration":359,"passed_time":0.1642977465,"remaining_time":0.2920848827},
{"learn":[4.280278245],"iteration":360,"passed_time":0.1645805307,"remaining_time":0.2913212163},
{"learn":[4.279941283],"iteration":361,"passed_time":0.1650073526,"remaining_time":0.2908140635},
{"learn":[4.274426275],"iteration":362,"passed_time":0.1652598042,"remaining_time":0.2900013644},
{"learn":[4.273567658],"iteration":363,"passed_time":0.16548134,"remaining_time":0.2891377259},
{"learn":[4.269488271],"iteration":364,"passed_time":0.1658730379,"remaining_time":0.2885736412},
{"learn":[4.266838205],"iteration":365,"passed_time":0.1661216563,"remaining_time":0.2877626505},
{"learn":[4.263456509],"iteration":366,"passed_time":0.1663923574,"remaining_time":0.2869928126},
{"learn":[4.260360204],"iteration":367,"passed_time":0.1666982242,"remaining_time":0.2862860807},
{"learn":[4.255120549],"iteration":368,"passed_time":0.1669530924,"remaining_time":0.2854943125},
{"learn":[4.252582211],"iteration":369,"passed_time":0.1672247519,"remaining_time":0.2847340369},
{"learn":[4.247857931],"iteration":370,"passed_time":0.1674744535,"remaining_time":0.2839391679},
{"learn":[4.245288911],"iteration":371,"passed_time":0.1677457796,"remaining_time":0.2831837355},
{"learn":[4.24048515],"iteration":372,"passed_time":0.1681466023,"remaining_time":0.2826485781},
{"learn":[4.2378365],"iteration":373,"passed_time":0.1684091786,"remaining_time":0.2818827428},
{"learn":[4.236751063],"iteration":374,"passed_time":0.1686577137,"remaining_time":0.2810961895},
{"learn":[4.233240093],"iteration":375,"passed_time":0.1689417894,"remaining_time":0.2803714803},
{"learn":[4.230358421],"iteration":376,"passed_time":0.1692103239,"remaining_time":0.2796234266},
{"learn":[4.225853583],"iteration":377,"passed_time":0.1694767335,"remaining_time":0.2788744133},
{"learn":[4.224702126],"iteration":378,"passed_time":0.1697203104,"remaining_time":0.2780905349},
{"learn":[4.224361982],"iteration":379,"passed_time":0.1700097193,"remaining_time":0.2773842789},
{"learn":[4.223787954],"iteration":380,"passed_time":0.170295295,"remaining_time":0.2766739833},
{"learn":[4.22144054],"iteration":381,"passed_time":0.1705486633,"remaining_time":0.275913806},
{"learn":[4.217739335],"iteration":382,"passed_time":0.1708001982,"remaining_time":0.275153322},
{"learn":[4.215611665],"iteration":383,"passed_time":0.1710781908,"remaining_time":0.2744379311},
{"learn":[4.210236863],"iteration":384,"passed_time":0.1713528085,"remaining_time":0.2737194214},
{"learn":[4.208454294],"iteration":385,"passed_time":0.1716101767,"remaining_time":0.2729757732},
{"learn":[4.207446501],"iteration":386,"passed_time":0.1718667115,"remaining_time":0.2722333182},
{"learn":[4.204985442],"iteration":387,"passed_time":0.1721234546,"remaining_time":0.2714936965},
{"learn":[4.202796622],"iteration":388,"passed_time":0.1724101553,"remaining_time":0.2708036116},
{"learn":[4.199774004],"iteration":389,"passed_time":0.1726551905,"remaining_time":0.2700504261},
{"learn":[4.199458358],"iteration":390,"passed_time":0.1728819761,"remaining_time":0.2692714155},
{"learn":[4.19751254],"iteration":391,"passed_time":0.1731333861,"remaining_time":0.2685334151},
{"learn":[4.195201346],"iteration":392,"passed_time":0.1734387529,"remaining_time":0.2678812291},
{"learn":[4.190593508],"iteration":393,"passed_time":0.1736892462,"remaining_time":0.2671464041},
{"learn":[4.187212054],"iteration":394,"passed_time":0.1739691555,"remaining_time":0.2664590862},
{"learn":[4.184984466],"iteration":395,"passed_time":0.1743297708,"remaining_time":0.2658969232},
{"learn":[4.182832144],"iteration":396,"passed_time":0.1746330961,"remaining_time":0.265248758},
{"learn":[4.179752812],"iteration":397,"passed_time":0.1748867977,"remaining_time":0.2645272668},
{"learn":[4.17878934],"iteration":398,"passed_time":0.1751592071,"remaining_time":0.2638362994},
{"learn":[4.174548229],"iteration":399,"passed_time":0.1754392413,"remaining_time":0.2631588619},
{"learn":[4.168872556],"iteration":400,"passed_time":0.1756901929,"remaining_time":0.262439964},
{"learn":[4.163926494],"iteration":401,"passed_time":0.1759318532,"remaining_time":0.2617095726},
{"learn":[4.159485076],"iteration":402,"passed_time":0.1762171372,"remaining_time":0.2610462306},
{"learn":[4.155926102],"iteration":403,"passed_time":0.1764636306,"remaining_time":0.2603275343},
{"learn":[4.153540115],"iteration":404,"passed_time":0.1767277486,"remaining_time":0.2596370628},
{"learn":[4.150983044],"iteration":405,"passed_time":0.1769646173,"remaining_time":0.2589088243},
{"learn":[4.146539132],"iteration":406,"passed_time":0.1772373184,"remaining_time":0.2582352083},
{"learn":[4.144869174],"iteration":407,"passed_time":0.1782961235,"remaining_time":0.2587041792},
{"learn":[4.142825962],"iteration":408,"passed_time":0.1786684469,"remaining_time":0.2581737215},
{"learn":[4.142467378],"iteration":409,"passed_time":0.1789147737,"remaining_time":0.2574627231},
{"learn":[4.141800768],"iteration":410,"passed_time":0.179203016,"remaining_time":0.2568140545},
{"learn":[4.140107084],"iteration":411,"passed_time":0.1794585925,"remaining_time":0.2561205155},
{"learn":[4.136243196],"iteration":412,"passed_time":0.1797381267,"remaining_time":0.2554631486},
{"learn":[4.133618439],"iteration":413,"passed_time":0.1799878701,"remaining_time":0.2547654393},
{"learn":[4.131053025],"iteration":414,"passed_time":0.1803698599,"remaining_time":0.2542563085},
{"learn":[4.128379975],"iteration":415,"passed_time":0.180653269,"remaining_time":0.2536093969},
{"learn":[4.127068571],"iteration":416,"passed_time":0.1810115511,"remaining_time":0.2530689072},
{"learn":[4.125969877],"iteration":417,"passed_time":0.1812438783,"remaining_time":0.2523539166},
{"learn":[4.123893633],"iteration":418,"passed_time":0.1815005381,"remaining_time":0.2516749705},
{"learn":[4.119643722],"iteration":419,"passed_time":0.1817658227,"remaining_time":0.2510099456},
{"learn":[4.11465686],"iteration":420,"passed_time":0.1819865668,"remaining_time":0.2502855634},
{"learn":[4.111565986],"iteration":421,"passed_time":0.1822131441,"remaining_time":0.2495715575},
{"learn":[4.106322452],"iteration":422,"passed_time":0.1824608458,"remaining_time":0.2488886715},
{"learn":[4.104222175],"iteration":423,"passed_time":0.1827307136,"remaining_time":0.2482379506},
{"learn":[4.103008002],"iteration":424,"passed_time":0.1829899984,"remaining_time":0.2475747037},
{"learn":[4.099176337],"iteration":425,"passed_time":0.1832638244,"remaining_time":0.2469329465},
{"learn":[4.096525716],"iteration":426,"passed_time":0.1835604832,"remaining_time":0.2463235524},
{"learn":[4.094967724],"iteration":427,"passed_time":0.1838046017,"remaining_time":0.2456454022},
{"learn":[4.094683584],"iteration":428,"passed_time":0.1840705529,"remaining_time":0.244998335},
{"learn":[4.091096563],"iteration":429,"passed_time":0.1843256711,"remaining_time":0.2443386803},
{"learn":[4.089178677],"iteration":430,"passed_time":0.1846134135,"remaining_time":0.2437239728},
{"learn":[4.085335077],"iteration":431,"passed_time":0.1848834479,"remaining_time":0.2430874963},
{"learn":[4.084852122],"iteration":432,"passed_time":0.185145066,"remaining_time":0.2424416914},
{"learn":[4.080322952],"iteration":433,"passed_time":0.1854355999,"remaining_time":0.2418353676},
{"learn":[4.077449519],"iteration":434,"passed_time":0.1857109259,"remaining_time":0.2412107428},
{"learn":[4.076568374],"iteration":435,"passed_time":0.185956086,"remaining_time":0.2405486984},
{"learn":[4.076071793],"iteration":436,"passed_time":0.1861915797,"remaining_time":0.2398761084},
{"learn":[4.075027644],"iteration":437,"passed_time":0.1864410731,"remaining_time":0.2392234773},
{"learn":[4.07020837],"iteration":438,"passed_time":0.186695983,"remaining_time":0.2385796046},
{"learn":[4.06833694],"iteration":439,"passed_time":0.1869693507,"remaining_time":0.2379609918},
{"learn":[4.063936568],"iteration":440,"passed_time":0.187218594,"remaining_time":0.2373133652},
{"learn":[4.061734926],"iteration":441,"passed_time":0.1875257525,"remaining_time":0.2367406559},
{"learn":[4.060815619],"iteration":442,"passed_time":0.1877835373,"remaining_time":0.2361070661},
{"learn":[4.056407489],"iteration":443,"passed_time":0.1881309031,"remaining_time":0.2355873471},
{"learn":[4.05238936],"iteration":444,"passed_time":0.1885183511,"remaining_time":0.2351183929},
{"learn":[4.049685254],"iteration":445,"passed_time":0.1888150932,"remaining_time":0.2345371336},
{"learn":[4.045162016],"iteration":446,"passed_time":0.1890667531,"remaining_time":0.2339013747},
{"learn":[4.042955482],"iteration":447,"passed_time":0.1893330793,"remaining_time":0.2332854013},
{"learn":[4.041467663],"iteration":448,"passed_time":0.1896002806,"remaining_time":0.2326720592},
{"learn":[4.038920476],"iteration":449,"passed_time":0.1898740233,"remaining_time":0.2320682507},
{"learn":[4.036694383],"iteration":450,"passed_time":0.1901101836,"remaining_time":0.231420157},
{"learn":[4.034999007],"iteration":451,"passed_time":0.1903624686,"remaining_time":0.2307934354},
{"learn":[4.031928018],"iteration":452,"passed_time":0.1906767519,"remaining_time":0.2302432302},
{"learn":[4.028718143],"iteration":453,"passed_time":0.1909879936,"remaining_time":0.2296904064},
{"learn":[4.027401978],"iteration":454,"passed_time":0.1912939021,"remaining_time":0.2291322564},
{"learn":[4.025930598],"iteration":455,"passed_time":0.1916006439,"remaining_time":0.2285762068},
{"learn":[4.021074523],"iteration":456,"passed_time":0.1919386349,"remaining_time":0.228058378},
{"learn":[4.020268486],"iteration":457,"passed_time":0.1922037528,"remaining_time":0.2274550962},
{"learn":[4.017986361],"iteration":458,"passed_time":0.1924389549,"remaining_time":0.2268180275},
{"learn":[4.014814804],"iteration":459,"passed_time":0.1927351553,"remaining_time":0.2262543128},
{"learn":[4.009704796],"iteration":460,"passed_time":0.1930736047,"remaining_time":0.225741156},
{"learn":[4.008440457],"iteration":461,"passed_time":0.1933453058,"remaining_time":0.225151027},
{"learn":[4.004854849],"iteration":462,"passed_time":0.1936343814,"remaining_time":0.2245824251},
{"learn":[4.000898028],"iteration":463,"passed_time":0.1939275402,"remaining_time":0.2240197448},
{"learn":[3.996617985],"iteration":464,"passed_time":0.194162534,"remaining_time":0.2233913025},
{"learn":[3.995443319],"iteration":465,"passed_time":0.1944016526,"remaining_time":0.2227692757},
{"learn":[3.990771995],"iteration":466,"passed_time":0.1947586014,"remaining_time":0.2222833716},
{"learn":[3.989249359],"iteration":467,"passed_time":0.1950959258,"remaining_time":0.2217757105},
{"learn":[3.986599538],"iteration":468,"passed_time":0.195349294,"remaining_time":0.2211737209},
{"learn":[3.985628919],"iteration":469,"passed_time":0.1956317865,"remaining_time":0.2206060571},
{"learn":[3.985086112],"iteration":470,"passed_time":0.1959420282,"remaining_time":0.2200707705},
{"learn":[3.98466839],"iteration":471,"passed_time":0.1963018936,"remaining_time":0.2195919488},
{"learn":[3.984233894],"iteration":472,"passed_time":0.1966165519,"remaining_time":0.2190632619},
{"learn":[3.981855845],"iteration":473,"passed_time":0.1968412543,"remaining_time":0.2184356535},
{"learn":[3.978684264],"iteration":474,"passed_time":0.1970841228,"remaining_time":0.2178298199},
{"learn":[3.974361269],"iteration":475,"passed_time":0.1973369494,"remaining_time":0.2172364737},
{"learn":[3.972074049],"iteration":476,"passed_time":0.197577193,"remaining_time":0.2166307588},
{"learn":[3.97191982],"iteration":477,"passed_time":0.1978367694,"remaining_time":0.2160476854},
{"learn":[3.969616848],"iteration":478,"passed_time":0.1980706382,"remaining_time":0.215438001},
{"learn":[3.968533527],"iteration":479,"passed_time":0.1983050069,"remaining_time":0.2148304242},
{"learn":[3.967568753],"iteration":480,"passed_time":0.1985349175,"remaining_time":0.2142195887},
{"learn":[3.966232553],"iteration":481,"passed_time":0.1987811609,"remaining_time":0.2136278866},
{"learn":[3.961522393],"iteration":482,"passed_time":0.1990459872,"remaining_time":0.2130575059},
{"learn":[3.955829553],"iteration":483,"passed_time":0.1992899807,"remaining_time":0.2124661777},
{"learn":[3.954248095],"iteration":484,"passed_time":0.1995370574,"remaining_time":0.2118795558},
{"learn":[3.951922606],"iteration":485,"passed_time":0.1997945506,"remaining_time":0.2113053477},
{"learn":[3.94978202],"iteration":486,"passed_time":0.2000494604,"remaining_time":0.2107297191},
{"learn":[3.949518999],"iteration":487,"passed_time":0.200290329,"remaining_time":0.2101406731},
{"learn":[3.945431216],"iteration":488,"passed_time":0.2005349058,"remaining_time":0.2095569261},
{"learn":[3.943249086],"iteration":489,"passed_time":0.2007819409,"remaining_time":0.2089771222},
{"learn":[3.941981548],"iteration":490,"passed_time":0.2010740998,"remaining_time":0.2084454517},
{"learn":[3.936600517],"iteration":491,"passed_time":0.2013040103,"remaining_time":0.2078504822},
{"learn":[3.934476885],"iteration":492,"passed_time":0.2015412123,"remaining_time":0.2072644922},
{"learn":[3.93045798],"iteration":493,"passed_time":0.2017878724,"remaining_time":0.2066896021},
{"learn":[3.925977375],"iteration":494,"passed_time":0.2020274077,"remaining_time":0.2061087695},
{"learn":[3.92457993],"iteration":495,"passed_time":0.203041714,"remaining_time":0.2063165804},
{"learn":[3.919849146],"iteration":496,"passed_time":0.2033038737,"remaining_time":0.2057582464},
{"learn":[3.919681964],"iteration":497,"passed_time":0.2036258235,"remaining_time":0.2052613722},
{"learn":[3.917633027],"iteration":498,"passed_time":0.203992147,"remaining_time":0.2048097508},
{"learn":[3.916616419],"iteration":499,"passed_time":0.2043550957,"remaining_time":0.2043550957},
{"learn":[3.912896166],"iteration":500,"passed_time":0.2046156304,"remaining_time":0.2037988015},
{"learn":[3.912769674],"iteration":501,"passed_time":0.2048483325,"remaining_time":0.2032160749},
{"learn":[3.909373788],"iteration":502,"passed_time":0.2051334083,"remaining_time":0.2026864889},
{"learn":[3.906706036],"iteration":503,"passed_time":0.2053973179,"remaining_time":0.202137043},
{"learn":[3.903895664],"iteration":504,"passed_time":0.2056429364,"remaining_time":0.201570799},
{"learn":[3.902982967],"iteration":505,"passed_time":0.2058799717,"remaining_time":0.2009974427},
{"learn":[3.900905528],"iteration":506,"passed_time":0.2061046324,"remaining_time":0.2004133802},
{"learn":[3.897463465],"iteration":507,"passed_time":0.2065539121,"remaining_time":0.2000482771},
{"learn":[3.895918033],"iteration":508,"passed_time":0.2069120275,"remaining_time":0.1995949028},
{"learn":[3.893921936],"iteration":509,"passed_time":0.2072893092,"remaining_time":0.1991603166},
{"learn":[3.890237934],"iteration":510,"passed_time":0.2075441774,"remaining_time":0.1986088116},
{"learn":[3.887311613],"iteration":511,"passed_time":0.2078396695,"remaining_time":0.198097185},
{"learn":[3.884869735],"iteration":512,"passed_time":0.2081182454,"remaining_time":0.1975703421},
{"learn":[3.882101231],"iteration":513,"passed_time":0.2083741136,"remaining_time":0.1970229946},
{"learn":[3.88060368],"iteration":514,"passed_time":0.2086228153,"remaining_time":0.1964700299},
{"learn":[3.877726076],"iteration":515,"passed_time":0.208896058,"remaining_time":0.1959412637},
{"learn":[3.874938145],"iteration":516,"passed_time":0.2092215077,"remaining_time":0.1954622596},
{"learn":[3.874340833],"iteration":517,"passed_time":0.2094711677,"remaining_time":0.1949133259},
{"learn":[3.873105224],"iteration":518,"passed_time":0.2097322024,"remaining_time":0.1943760874},
{"learn":[3.869800236],"iteration":519,"passed_time":0.2100005286,"remaining_time":0.1938466418},
{"learn":[3.867932518],"iteration":520,"passed_time":0.2102506469,"remaining_time":0.1933014585},
{"learn":[3.866666962],"iteration":521,"passed_time":0.2105036818,"remaining_time":0.1927600765},
{"learn":[3.865527652],"iteration":522,"passed_time":0.2107603417,"remaining_time":0.1922231032},
{"learn":[3.861900081],"iteration":523,"passed_time":0.211010835,"remaining_time":0.1916815982},
{"learn":[3.858502887],"iteration":524,"passed_time":0.2112858693,"remaining_time":0.1911634056},
{"learn":[3.858335097],"iteration":525,"passed_time":0.2116958584,"remaining_time":0.1907677507},
{"learn":[3.855719306],"iteration":526,"passed_time":0.2120149332,"remaining_time":0.1902904429},
{"learn":[3.855137428],"iteration":527,"passed_time":0.2122880093,"remaining_time":0.1897726144},
{"learn":[3.851985706],"iteration":528,"passed_time":0.2125564605,"remaining_time":0.1892515933},
{"learn":[3.851051809],"iteration":529,"passed_time":0.212787746,"remaining_time":0.1886985672},
{"learn":[3.850679146],"iteration":530,"passed_time":0.2130609887,"remaining_time":0.1881838111},
{"learn":[3.848179484],"iteration":531,"passed_time":0.2133731887,"remaining_time":0.1877042337},
{"learn":[3.844551071],"iteration":532,"passed_time":0.2136099324,"remaining_time":0.1871591715},
{"learn":[3.841604794],"iteration":533,"passed_time":0.2138713837,"remaining_time":0.1866368255},
{"learn":[3.83969656],"iteration":534,"passed_time":0.214088128,"remaining_time":0.1860765972},
{"learn":[3.836811463],"iteration":535,"passed_time":0.2143855367,"remaining_time":0.1855874795},
{"learn":[3.834182551],"iteration":536,"passed_time":0.2146503213,"remaining_time":0.1850709474},
{"learn":[3.828012842],"iteration":537,"passed_time":0.2148945648,"remaining_time":0.1845377118},
{"learn":[3.826636176],"iteration":538,"passed_time":0.21513835,"remaining_time":0.1840051565},
{"learn":[3.826189798],"iteration":539,"passed_time":0.216051034,"remaining_time":0.1840434734},
{"learn":[3.824104738],"iteration":540,"passed_time":0.2163460678,"remaining_time":0.1835542424},
{"learn":[3.82300218],"iteration":541,"passed_time":0.2166322685,"remaining_time":0.1830582638},
{"learn":[3.817146402],"iteration":542,"passed_time":0.2169048029,"remaining_time":0.182551556},
{"learn":[3.814638044],"iteration":543,"passed_time":0.2171870037,"remaining_time":0.1820538119},
{"learn":[3.812979573],"iteration":544,"passed_time":0.2174494134,"remaining_time":0.181540336},
{"learn":[3.811938825],"iteration":545,"passed_time":0.2176845321,"remaining_time":0.1810050872},
{"learn":[3.811479418],"iteration":546,"passed_time":0.2179230674,"remaining_time":0.1804737652},
{"learn":[3.80742981],"iteration":547,"passed_time":0.2181720608,"remaining_time":0.1799521377},
{"learn":[3.805097043],"iteration":548,"passed_time":0.2183765553,"remaining_time":0.179394948},
{"learn":[3.801577232],"iteration":549,"passed_time":0.2186470065,"remaining_time":0.1788930053},
{"learn":[3.799762083],"iteration":550,"passed_time":0.2190065386,"remaining_time":0.1784644933},
{"learn":[3.796393455],"iteration":551,"passed_time":0.2192686982,"remaining_time":0.1779572044},
{"learn":[3.793486459],"iteration":552,"passed_time":0.2196248138,"remaining_time":0.1775267482},
{"learn":[3.792006091],"iteration":553,"passed_time":0.2198964315,"remaining_time":0.1770285351},
{"learn":[3.78932128],"iteration":554,"passed_time":0.2201437166,"remaining_time":0.1765116286},
{"learn":[3.787581812],"iteration":555,"passed_time":0.2204033347,"remaining_time":0.1760055406},
{"learn":[3.785308865],"iteration":556,"passed_time":0.2206460782,"remaining_time":0.1754869168},
{"learn":[3.78465475],"iteration":557,"passed_time":0.2209340705,"remaining_time":0.175005124},
{"learn":[3.780498869],"iteration":558,"passed_time":0.2212089799,"remaining_time":0.1745137033},
{"learn":[3.778734909],"iteration":559,"passed_time":0.2214469319,"remaining_time":0.1739940179},
{"learn":[3.778652349],"iteration":560,"passed_time":0.221741924,"remaining_time":0.1735199726},
{"learn":[3.777928006],"iteration":561,"passed_time":0.2220015421,"remaining_time":0.1730189954},
{"learn":[3.776131406],"iteration":562,"passed_time":0.2222679933,"remaining_time":0.1725241795},
{"learn":[3.772925617],"iteration":563,"passed_time":0.2225501525,"remaining_time":0.1720423164},
{"learn":[3.7727745],"iteration":564,"passed_time":0.2227807713,"remaining_time":0.1715214788},
{"learn":[3.771763073],"iteration":565,"passed_time":0.2230253898,"remaining_time":0.1710124014},
{"learn":[3.768738162],"iteration":566,"passed_time":0.2232751331,"remaining_time":0.1705081705},
{"learn":[3.767220794],"iteration":567,"passed_time":0.2235361262,"remaining_time":0.1700133917},
{"learn":[3.766691102],"iteration":568,"passed_time":0.2237904944,"remaining_time":0.1695144167},
{"learn":[3.766259335],"iteration":569,"passed_time":0.2240598622,"remaining_time":0.1690276154},
{"learn":[3.76116362],"iteration":570,"passed_time":0.2244878925,"remaining_time":0.1686607809},
{"learn":[3.758633056],"iteration":571,"passed_time":0.2247352609,"remaining_time":0.1681585519},
{"learn":[3.754603809],"iteration":572,"passed_time":0.225031753,"remaining_time":0.1676938194},
{"learn":[3.754070549],"iteration":573,"passed_time":0.2252847462,"remaining_time":0.1671973901},
{"learn":[3.750534319],"iteration":574,"passed_time":0.225543906,"remaining_time":0.1667063653},
{"learn":[3.746491516],"iteration":575,"passed_time":0.2257861079,"remaining_time":0.1662036628},
{"learn":[3.744210544],"iteration":576,"passed_time":0.2260280181,"remaining_time":0.1657016493},
{"learn":[3.742929991],"iteration":577,"passed_time":0.2263092189,"remaining_time":0.1652292221},
{"learn":[3.740402992],"iteration":578,"passed_time":0.2265449627,"remaining_time":0.1647244029},
{"learn":[3.739644243],"iteration":579,"passed_time":0.2267773315,"remaining_time":0.1642180676},
{"learn":[3.737529404],"iteration":580,"passed_time":0.2270192,"remaining_time":0.1637195264},
{"learn":[3.737196923],"iteration":581,"passed_time":0.2272504855,"remaining_time":0.1632142662},
{"learn":[3.733954464],"iteration":582,"passed_time":0.227534478,"remaining_time":0.1627476455},
{"learn":[3.731608623],"iteration":583,"passed_time":0.2277734299,"remaining_time":0.1622495665},
{"learn":[3.729843952],"iteration":584,"passed_time":0.2280615472,"remaining_time":0.1617872515},
{"learn":[3.727223798],"iteration":585,"passed_time":0.2283170404,"remaining_time":0.1613024825},
{"learn":[3.725351667],"iteration":586,"passed_time":0.2286183241,"remaining_time":0.1608507118},
{"learn":[3.725026912],"iteration":587,"passed_time":0.2289012749,"remaining_time":0.1603866076},
{"learn":[3.721974565],"iteration":588,"passed_time":0.2291520182,"remaining_time":0.1599006443},
{"learn":[3.720269493],"iteration":589,"passed_time":0.2294363439,"remaining_time":0.1594388153},
{"learn":[3.718907466],"iteration":590,"passed_time":0.229698212,"remaining_time":0.1589620452},
{"learn":[3.715602912],"iteration":591,"passed_time":0.2299554134,"remaining_time":0.1584827849},
{"learn":[3.714463059],"iteration":592,"passed_time":0.2302192814,"remaining_time":0.1580088491},
{"learn":[3.710802077],"iteration":593,"passed_time":0.2304643582,"remaining_time":0.1575227768},
{"learn":[3.708032435],"iteration":594,"passed_time":0.2307000603,"remaining_time":0.1570311335},
{"learn":[3.703788939],"iteration":595,"passed_time":0.2309681365,"remaining_time":0.1565622938},
{"learn":[3.702500944],"iteration":596,"passed_time":0.2312520872,"remaining_time":0.1561048428},
{"learn":[3.698196925],"iteration":597,"passed_time":0.2315014139,"remaining_time":0.1556246963},
{"learn":[3.69658891],"iteration":598,"passed_time":0.2317489073,"remaining_time":0.1551440932},
{"learn":[3.696124066],"iteration":599,"passed_time":0.2319973174,"remaining_time":0.1546648782},
{"learn":[3.693537052],"iteration":600,"passed_time":0.2322695184,"remaining_time":0.1542022261},
{"learn":[3.691343275],"iteration":601,"passed_time":0.2325533442,"remaining_time":0.153747892},
{"learn":[3.690973831],"iteration":602,"passed_time":0.2328272119,"remaining_time":0.1532875674},
{"learn":[3.686151073],"iteration":603,"passed_time":0.2337164382,"remaining_time":0.1532313072},
{"learn":[3.683921982],"iteration":604,"passed_time":0.2340048889,"remaining_time":0.1527800514},
{"learn":[3.679975271],"iteration":605,"passed_time":0.2344211694,"remaining_time":0.1524124435},
{"learn":[3.674047638],"iteration":606,"passed_time":0.2346935372,"remaining_time":0.1519514994},
{"learn":[3.673151794],"iteration":607,"passed_time":0.2349358224,"remaining_time":0.1514717802},
{"learn":[3.670953108],"iteration":608,"passed_time":0.2352223564,"remaining_time":0.1510212502},
{"learn":[3.6703947],"iteration":609,"passed_time":0.2354630167,"remaining_time":0.1505419287},
{"learn":[3.668433805],"iteration":610,"passed_time":0.2357437175,"remaining_time":0.1500888807},
{"learn":[3.668304956],"iteration":611,"passed_time":0.2359852111,"remaining_time":0.1496115391},
{"learn":[3.667880012],"iteration":612,"passed_time":0.2362488707,"remaining_time":0.1491489608},
{"learn":[3.667282264],"iteration":613,"passed_time":0.2365158219,"remaining_time":0.1486890998},
{"learn":[3.664611483],"iteration":614,"passed_time":0.2367551906,"remaining_time":0.148212599},
{"learn":[3.662543394],"iteration":615,"passed_time":0.2369792679,"remaining_time":0.1477273359},
{"learn":[3.659041959],"iteration":616,"passed_time":0.2372122201,"remaining_time":0.1472484283},
{"learn":[3.656868545],"iteration":617,"passed_time":0.2374440889,"remaining_time":0.1467696472},
{"learn":[3.654785614],"iteration":618,"passed_time":0.2377297479,"remaining_time":0.1463247721},
{"learn":[3.654566096],"iteration":619,"passed_time":0.2379722415,"remaining_time":0.1458539544},
{"learn":[3.651007045],"iteration":620,"passed_time":0.2382184016,"remaining_time":0.1453861098},
{"learn":[3.648921786],"iteration":621,"passed_time":0.2384741448,"remaining_time":0.1449248018},
{"learn":[3.647655706],"iteration":622,"passed_time":0.2387322212,"remaining_time":0.1444655656},
{"learn":[3.647241144],"iteration":623,"passed_time":0.2389734231,"remaining_time":0.1439968062},
{"learn":[3.644195689],"iteration":624,"passed_time":0.2392104585,"remaining_time":0.1435262751},
{"learn":[3.642632246],"iteration":625,"passed_time":0.2394722848,"remaining_time":0.1430713012},
{"learn":[3.642523322],"iteration":626,"passed_time":0.2397976095,"remaining_time":0.1426547182},
{"learn":[3.641494659],"iteration":627,"passed_time":0.2400729771,"remaining_time":0.1422088336},
{"learn":[3.63976496],"iteration":628,"passed_time":0.2404095932,"remaining_time":0.141799617},
{"learn":[3.637945652],"iteration":629,"passed_time":0.2407026687,"remaining_time":0.1413650594},
{"learn":[3.636233667],"iteration":630,"passed_time":0.2409485371,"remaining_time":0.1409033442},
{"learn":[3.635304404],"iteration":631,"passed_time":0.2412076552,"remaining_time":0.1404500271},
{"learn":[3.632234951],"iteration":632,"passed_time":0.2414734815,"remaining_time":0.1400012128},
{"learn":[3.631630987],"iteration":633,"passed_time":0.2419094282,"remaining_time":0.1396511841},
{"learn":[3.630301009],"iteration":634,"passed_time":0.2421989205,"remaining_time":0.1392167023},
{"learn":[3.629077964],"iteration":635,"passed_time":0.2424620385,"remaining_time":0.1387675818},
{"learn":[3.628004522],"iteration":636,"passed_time":0.2427147401,"remaining_time":0.1383131093},
{"learn":[3.625062876],"iteration":637,"passed_time":0.2429921077,"remaining_time":0.1378732649},
{"learn":[3.624917986],"iteration":638,"passed_time":0.2432867665,"remaining_time":0.1374436975},
{"learn":[3.622887087],"iteration":639,"passed_time":0.2435555927,"remaining_time":0.1370000209},
{"learn":[3.621220865],"iteration":640,"passed_time":0.2438350019,"remaining_time":0.136562817},
{"learn":[3.621143844],"iteration":641,"passed_time":0.2440863285,"remaining_time":0.1361104449},
{"learn":[3.620822821],"iteration":642,"passed_time":0.2443749458,"remaining_time":0.1356794023},
{"learn":[3.619202826],"iteration":643,"passed_time":0.2446362722,"remaining_time":0.1352337157},
{"learn":[3.618204882],"iteration":644,"passed_time":0.2448926404,"remaining_time":0.1347858718},
{"learn":[3.614259666],"iteration":645,"passed_time":0.2451496752,"remaining_time":0.1343389861},
{"learn":[3.613415661],"iteration":646,"passed_time":0.2454887495,"remaining_time":0.1339374476},
{"learn":[3.611096773],"iteration":647,"passed_time":0.2457346596,"remaining_time":0.1334854941},
{"learn":[3.610820695],"iteration":648,"passed_time":0.2460156521,"remaining_time":0.1330531493},
{"learn":[3.609290065],"iteration":649,"passed_time":0.2462661038,"remaining_time":0.1326048251},
{"learn":[3.60897947],"iteration":650,"passed_time":0.2466511352,"remaining_time":0.1322292568},
{"learn":[3.606570702],"iteration":651,"passed_time":0.2468957953,"remaining_time":0.1317787374},
{"learn":[3.606292637],"iteration":652,"passed_time":0.2471792878,"remaining_time":0.1313494837},
{"learn":[3.602753838],"iteration":653,"passed_time":0.247471655,"remaining_time":0.130925371},
{"learn":[3.599755869],"iteration":654,"passed_time":0.2477830217,"remaining_time":0.1305116679},
{"learn":[3.599509575],"iteration":655,"passed_time":0.2480485146,"remaining_time":0.1300742211},
{"learn":[3.595337722],"iteration":656,"passed_time":0.2483360903,"remaining_time":0.1296488264},
{"learn":[3.595168561],"iteration":657,"passed_time":0.2485732923,"remaining_time":0.1291976686},
{"learn":[3.59290559],"iteration":658,"passed_time":0.2489220747,"remaining_time":0.1288048975},
{"learn":[3.592015928],"iteration":659,"passed_time":0.2492040255,"remaining_time":0.1283778313},
{"learn":[3.590680403],"iteration":660,"passed_time":0.2494514355,"remaining_time":0.1279334896},
{"learn":[3.590361532],"iteration":661,"passed_time":0.2496828044,"remaining_time":0.1274815527},
{"learn":[3.589069739],"iteration":662,"passed_time":0.2499067984,"remaining_time":0.1270265325},
{"learn":[3.585010186],"iteration":663,"passed_time":0.2501371673,"remaining_time":0.126575434},
{"learn":[3.582997552],"iteration":664,"passed_time":0.2503633696,"remaining_time":0.1261229005},
{"learn":[3.582119256],"iteration":665,"passed_time":0.2506400289,"remaining_time":0.1256963508},
{"learn":[3.579019356],"iteration":666,"passed_time":0.2509168132,"remaining_time":0.125270313},
{"learn":[3.57719559],"iteration":667,"passed_time":0.2512021389,"remaining_time":0.1248489672},
{"learn":[3.574050046],"iteration":668,"passed_time":0.2514755483,"remaining_time":0.1244221323},
{"learn":[3.572204518],"iteration":669,"passed_time":0.2517179168,"remaining_time":0.1239804665},
{"learn":[3.569508025],"iteration":670,"passed_time":0.2519892013,"remaining_time":0.1235535726},
{"learn":[3.566268704],"iteration":671,"passed_time":0.2522831101,"remaining_time":0.1231381847},
{"learn":[3.562564052],"iteration":672,"passed_time":0.2525378533,"remaining_time":0.1227041278},
{"learn":[3.561173586],"iteration":673,"passed_time":0.2528516783,"remaining_time":0.1222991797},
{"learn":[3.559551904],"iteration":674,"passed_time":0.2531049215,"remaining_time":0.1218653326},
{"learn":[3.558593054],"iteration":675,"passed_time":0.2534389543,"remaining_time":0.1214707414},
{"learn":[3.555647008],"iteration":676,"passed_time":0.2536933225,"remaining_time":0.1210383208},
{"learn":[3.553100059],"iteration":677,"passed_time":0.2539320245,"remaining_time":0.1205989851},
{"learn":[3.55085578],"iteration":678,"passed_time":0.2541839761,"remaining_time":0.1201665042},
{"learn":[3.550737965],"iteration":679,"passed_time":0.2544513856,"remaining_time":0.1197418285},
{"learn":[3.549408772],"iteration":680,"passed_time":0.2546897126,"remaining_time":0.1193039917},
{"learn":[3.547390589],"iteration":681,"passed_time":0.2549299146,"remaining_time":0.1188676141},
{"learn":[3.54723575],"iteration":682,"passed_time":0.2551896576,"remaining_time":0.1184408806},
{"learn":[3.543988891],"iteration":683,"passed_time":0.2554526923,"remaining_time":0.1180161561},
{"learn":[3.543868508],"iteration":684,"passed_time":0.2557688922,"remaining_time":0.1176163519},
{"learn":[3.542752124],"iteration":685,"passed_time":0.2560164273,"remaining_time":0.1171853617},
{"learn":[3.541334315],"iteration":686,"passed_time":0.2562665039,"remaining_time":0.1167560637},
{"learn":[3.540208266],"iteration":687,"passed_time":0.2565301636,"remaining_time":0.1163334463},
{"learn":[3.537730983],"iteration":688,"passed_time":0.2567704905,"remaining_time":0.1159007584},
{"learn":[3.53419867],"iteration":689,"passed_time":0.2573115594,"remaining_time":0.1156037441},
{"learn":[3.532628335],"iteration":690,"passed_time":0.257615468,"remaining_time":0.1151999705},
{"learn":[3.532204987],"iteration":691,"passed_time":0.2579111268,"remaining_time":0.1147928136},
{"learn":[3.530618147],"iteration":692,"passed_time":0.2581597451,"remaining_time":0.1143651396},
{"learn":[3.528909306],"iteration":693,"passed_time":0.2584443209,"remaining_time":0.113953836},
{"learn":[3.526700678],"iteration":694,"passed_time":0.2586804396,"remaining_time":0.1135216318},
{"learn":[3.526439574],"iteration":695,"passed_time":0.2589369744,"remaining_time":0.1130989084},
{"learn":[3.525784216],"iteration":696,"passed_time":0.2592700906,"remaining_time":0.1127099533},
{"learn":[3.524112693],"iteration":697,"passed_time":0.2595626244,"remaining_time":0.1123035997},
{"learn":[3.522813541],"iteration":698,"passed_time":0.25979191,"remaining_time":0.1118703361},
{"learn":[3.519148203],"iteration":699,"passed_time":0.2601781497,"remaining_time":0.1115049213},
{"learn":[3.517236747],"iteration":700,"passed_time":0.260428518,"remaining_time":0.1110814934},
{"learn":[3.515603888],"iteration":701,"passed_time":0.2606706782,"remaining_time":0.1106550742},
{"learn":[3.51263524],"iteration":702,"passed_time":0.2609290047,"remaining_time":0.1102360091},
{"learn":[3.51123442],"iteration":703,"passed_time":0.261168415,"remaining_time":0.1098094472},
{"learn":[3.50828027],"iteration":704,"passed_time":0.2614275331,"remaining_time":0.1093916628},
{"learn":[3.508265537],"iteration":705,"passed_time":0.2615951953,"remaining_time":0.1089362428},
{"learn":[3.506774876],"iteration":706,"passed_time":0.2618442303,"remaining_time":0.1085153599},
{"learn":[3.50552068],"iteration":707,"passed_time":0.2620909737,"remaining_time":0.1080940174},
{"learn":[3.501973993],"iteration":708,"passed_time":0.2623408837,"remaining_time":0.1076744671},
{"learn":[3.498880354],"iteration":709,"passed_time":0.2625744192,"remaining_time":0.1072487064},
{"learn":[3.497370959],"iteration":710,"passed_time":0.2628594532,"remaining_time":0.1068444191},
{"learn":[3.496050455],"iteration":711,"passed_time":0.2631392791,"remaining_time":0.1064383601},
{"learn":[3.495630067],"iteration":712,"passed_time":0.2634114385,"remaining_time":0.1060295692},
{"learn":[3.49550669],"iteration":713,"passed_time":0.2636635985,"remaining_time":0.1056131501},
{"learn":[3.493652375],"iteration":714,"passed_time":0.2639298414,"remaining_time":0.1052028039},
{"learn":[3.491915684],"iteration":715,"passed_time":0.2641791681,"remaining_time":0.1047861505},
{"learn":[3.490303956],"iteration":716,"passed_time":0.2644840766,"remaining_time":0.1043919019},
{"learn":[3.488363853],"iteration":717,"passed_time":0.2647707773,"remaining_time":0.103990751},
{"learn":[3.485483936],"iteration":718,"passed_time":0.2650230622,"remaining_time":0.103576468},
{"learn":[3.483763466],"iteration":719,"passed_time":0.2653067213,"remaining_time":0.1031748361},
{"learn":[3.481642352],"iteration":720,"passed_time":0.265555673,"remaining_time":0.1027601009},
{"learn":[3.479826119],"iteration":721,"passed_time":0.2658090413,"remaining_time":0.1023475256},
{"learn":[3.478588728],"iteration":722,"passed_time":0.2660581597,"remaining_time":0.1019337624},
{"learn":[3.475390887],"iteration":723,"passed_time":0.2663503602,"remaining_time":0.1015368776},
{"learn":[3.472636852],"iteration":724,"passed_time":0.2666132699,"remaining_time":0.1011291713},
{"learn":[3.47061883],"iteration":725,"passed_time":0.2668869709,"remaining_time":0.1007259367},
{"learn":[3.46953149],"iteration":726,"passed_time":0.2671284228,"remaining_time":0.1003109483},
{"learn":[3.467217162],"iteration":727,"passed_time":0.2673788745,"remaining_time":0.09989979925},
{"learn":[3.465686216],"iteration":728,"passed_time":0.2676899495,"remaining_time":0.09951162732},
{"learn":[3.462631216],"iteration":729,"passed_time":0.2679291931,"remaining_time":0.09909709883},
{"learn":[3.461451053],"iteration":730,"passed_time":0.2681818114,"remaining_time":0.09868797163},
{"learn":[3.458950469],"iteration":731,"passed_time":0.2684577207,"remaining_time":0.09828779938},
{"learn":[3.458072145],"iteration":732,"passed_time":0.2687405882,"remaining_time":0.09789050074},
{"learn":[3.454364268],"iteration":733,"passed_time":0.2690465383,"remaining_time":0.09750187902},
{"learn":[3.453243406],"iteration":734,"passed_time":0.2693216977,"remaining_time":0.0971023808},
{"learn":[3.453017963],"iteration":735,"passed_time":0.2695682744,"remaining_time":0.09669296801},
{"learn":[3.45201581],"iteration":736,"passed_time":0.2698221843,"remaining_time":0.09628661395},
{"learn":[3.449510107],"iteration":737,"passed_time":0.2701026769,"remaining_time":0.09589011022},
{"learn":[3.447189189],"iteration":738,"passed_time":0.2703868776,"remaining_time":0.09549523012},
{"learn":[3.446423605],"iteration":739,"passed_time":0.2706588704,"remaining_time":0.09509635986},
{"learn":[3.445531987],"iteration":740,"passed_time":0.2708968224,"remaining_time":0.09468593387},
{"learn":[3.445328199],"iteration":741,"passed_time":0.2711383159,"remaining_time":0.09427720419},
{"learn":[3.443327544],"iteration":742,"passed_time":0.2713938508,"remaining_time":0.0938737815},
{"learn":[3.441475798],"iteration":743,"passed_time":0.2716358027,"remaining_time":0.09346608264},
{"learn":[3.439046501],"iteration":744,"passed_time":0.27186063,"remaining_time":0.09305296732},
{"learn":[3.435899469],"iteration":745,"passed_time":0.2721291229,"remaining_time":0.09265522414},
{"learn":[3.433988352],"iteration":746,"passed_time":0.272574611,"remaining_time":0.0923177732},
{"learn":[3.433413263],"iteration":747,"passed_time":0.2728256876,"remaining_time":0.09191453648},
{"learn":[3.429944699],"iteration":748,"passed_time":0.2730771393,"remaining_time":0.09151183172},
{"learn":[3.429291634],"iteration":749,"passed_time":0.273335799,"remaining_time":0.09111193301},
{"learn":[3.429175603],"iteration":750,"passed_time":0.2736186248,"remaining_time":0.09072042288},
{"learn":[3.428780323],"iteration":751,"passed_time":0.2738427439,"remaining_time":0.09030984106},
{"learn":[3.423893341],"iteration":752,"passed_time":0.2741233614,"remaining_time":0.0899182872},
{"learn":[3.421024316],"iteration":753,"passed_time":0.2745178925,"remaining_time":0.08956419306},
{"learn":[3.420969872],"iteration":754,"passed_time":0.2747908853,"remaining_time":0.08917055217},
{"learn":[3.419544785],"iteration":755,"passed_time":0.2750301289,"remaining_time":0.08876633789},
{"learn":[3.417057977],"iteration":756,"passed_time":0.2752663726,"remaining_time":0.08836159649},
{"learn":[3.415160245],"iteration":757,"passed_time":0.2755262407,"remaining_time":0.08796484201},
{"learn":[3.412854597],"iteration":758,"passed_time":0.2757768173,"remaining_time":0.08756549799},
{"learn":[3.410926347],"iteration":759,"passed_time":0.2760142693,"remaining_time":0.08716240084},
{"learn":[3.408963843],"iteration":760,"passed_time":0.2762655126,"remaining_time":0.08676407033},
{"learn":[3.407629634],"iteration":761,"passed_time":0.2764990897,"remaining_time":0.08636060808},
{"learn":[3.404384724],"iteration":762,"passed_time":0.2767947485,"remaining_time":0.08597687471},
{"learn":[3.403041656],"iteration":763,"passed_time":0.2770340755,"remaining_time":0.08557597096},
{"learn":[3.401101731],"iteration":764,"passed_time":0.2773294426,"remaining_time":0.08519270459},
{"learn":[3.400890668],"iteration":765,"passed_time":0.2775819775,"remaining_time":0.08479658322},
{"learn":[3.399289941],"iteration":766,"passed_time":0.2778140547,"remaining_time":0.08439462157},
{"learn":[3.399202366],"iteration":767,"passed_time":0.2780746728,"remaining_time":0.08400172406},
{"learn":[3.397447845],"iteration":768,"passed_time":0.2783305409,"remaining_time":0.08360774377},
{"learn":[3.394655341],"iteration":769,"passed_time":0.2786094085,"remaining_time":0.08322099215},
{"learn":[3.393228229],"iteration":770,"passed_time":0.278854777,"remaining_time":0.08282457059},
{"learn":[3.389691197],"iteration":771,"passed_time":0.2791382277,"remaining_time":0.08243978747},
{"learn":[3.389626772],"iteration":772,"passed_time":0.2793797213,"remaining_time":0.08204294533},
{"learn":[3.388480222],"iteration":773,"passed_time":0.2796347562,"remaining_time":0.08165045852},
{"learn":[3.388215066],"iteration":774,"passed_time":0.2798749998,"remaining_time":0.08125403219},
{"learn":[3.386324358],"iteration":775,"passed_time":0.2801329096,"remaining_time":0.08086310792},
{"learn":[3.383913061],"iteration":776,"passed_time":0.2804267351,"remaining_time":0.08048283387},
{"learn":[3.382839768],"iteration":777,"passed_time":0.2807075609,"remaining_time":0.08009907265},
{"learn":[3.381961844],"iteration":778,"passed_time":0.2809523461,"remaining_time":0.07970535107},
{"learn":[3.381521703],"iteration":779,"passed_time":0.2812825039,"remaining_time":0.07933609085},
{"learn":[3.380918963],"iteration":780,"passed_time":0.2815943706,"remaining_time":0.07896180175},
{"learn":[3.377139006],"iteration":781,"passed_time":0.2818494888,"remaining_time":0.07857185238},
{"learn":[3.376004372],"iteration":782,"passed_time":0.2821197733,"remaining_time":0.07818645058},
{"learn":[3.373826468],"iteration":783,"passed_time":0.2823959743,"remaining_time":0.0778029725},
{"learn":[3.373546786],"iteration":784,"passed_time":0.2826465509,"remaining_time":0.07741274961},
{"learn":[3.372109181],"iteration":785,"passed_time":0.2828906694,"remaining_time":0.07702112373},
{"learn":[3.370764924],"iteration":786,"passed_time":0.2831143718,"remaining_time":0.07662434713},
{"learn":[3.367833107],"iteration":787,"passed_time":0.2833584903,"remaining_time":0.07623350246},
{"learn":[3.36450404],"iteration":788,"passed_time":0.28362015,"remaining_time":0.07584772071},
{"learn":[3.361794558],"iteration":789,"passed_time":0.2839012675,"remaining_time":0.07546742553},
{"learn":[3.356880529],"iteration":790,"passed_time":0.2841661771,"remaining_time":0.07508309862},
{"learn":[3.353843509],"iteration":791,"passed_time":0.285144026,"remaining_time":0.07488630986},
{"learn":[3.353640253],"iteration":792,"passed_time":0.2854200187,"remaining_time":0.07450434283},
{"learn":[3.353055088],"iteration":793,"passed_time":0.2856564707,"remaining_time":0.07411238409},
{"learn":[3.351415617],"iteration":794,"passed_time":0.2859154221,"remaining_time":0.07372661829},
{"learn":[3.349169061],"iteration":795,"passed_time":0.2861664988,"remaining_time":0.07333915295},
{"learn":[3.346211014],"iteration":796,"passed_time":0.2864304084,"remaining_time":0.0729552985},
{"learn":[3.344560452],"iteration":797,"passed_time":0.2867475666,"remaining_time":0.07258522363},
{"learn":[3.344445461],"iteration":798,"passed_time":0.2870570584,"remaining_time":0.07221335261},
{"learn":[3.342608898],"iteration":799,"passed_time":0.2873783415,"remaining_time":0.07184458537},
{"learn":[3.339572899],"iteration":800,"passed_time":0.2877349986,"remaining_time":0.07148472501},
{"learn":[3.339309302],"iteration":801,"passed_time":0.2901237683,"remaining_time":0.07162656624},
{"learn":[3.33698088],"iteration":802,"passed_time":0.2906047555,"remaining_time":0.07129406828},
{"learn":[3.334746342],"iteration":803,"passed_time":0.2912938621,"remaining_time":0.07101193654},
{"learn":[3.332048511],"iteration":804,"passed_time":0.2919664692,"remaining_time":0.07072479689},
{"learn":[3.331932544],"iteration":805,"passed_time":0.2931333131,"remaining_time":0.07055566097},
{"learn":[3.330541133],"iteration":806,"passed_time":0.2937260056,"remaining_time":0.07024673989},
{"learn":[3.329124989],"iteration":807,"passed_time":0.294251575,"remaining_time":0.06992116633},
{"learn":[3.32583918],"iteration":808,"passed_time":0.29569087,"remaining_time":0.06981082344},
{"learn":[3.325287299],"iteration":809,"passed_time":0.2969100458,"remaining_time":0.0696455663},
{"learn":[3.322745162],"iteration":810,"passed_time":0.2977416486,"remaining_time":0.06938738791},
{"learn":[3.319733662],"iteration":811,"passed_time":0.2984249221,"remaining_time":0.06909345487},
{"learn":[3.318080007],"iteration":812,"passed_time":0.2989365335,"remaining_time":0.06875907965},
{"learn":[3.317179538],"iteration":813,"passed_time":0.3002252491,"remaining_time":0.06860183825},
{"learn":[3.315685949],"iteration":814,"passed_time":0.3006720705,"remaining_time":0.0682507154},
{"learn":[3.314944576],"iteration":815,"passed_time":0.3010389774,"remaining_time":0.06788133805},
{"learn":[3.312369052],"iteration":816,"passed_time":0.3018715386,"remaining_time":0.06761626874},
{"learn":[3.312321621],"iteration":817,"passed_time":0.3021904051,"remaining_time":0.067235518},
{"learn":[3.309465776],"iteration":818,"passed_time":0.3026413931,"remaining_time":0.06688411739},
{"learn":[3.308307377],"iteration":819,"passed_time":0.3042264758,"remaining_time":0.06678142152},
{"learn":[3.308076804],"iteration":820,"passed_time":0.305659396,"remaining_time":0.06664193895},
{"learn":[3.305643326],"iteration":821,"passed_time":0.3065603303,"remaining_time":0.06638411045},
{"learn":[3.304154814],"iteration":822,"passed_time":0.3073279765,"remaining_time":0.06609605327},
{"learn":[3.303076321],"iteration":823,"passed_time":0.3082526602,"remaining_time":0.06584037402},
{"learn":[3.301746372],"iteration":824,"passed_time":0.3088653939,"remaining_time":0.06551690173},
{"learn":[3.301345455],"iteration":825,"passed_time":0.3094814608,"remaining_time":0.0651934312},
{"learn":[3.299181039],"iteration":826,"passed_time":0.311111459,"remaining_time":0.0650813572},
{"learn":[3.297989357],"iteration":827,"passed_time":0.3120339344,"remaining_time":0.06481864338},
{"learn":[3.294775182],"iteration":828,"passed_time":0.3128415379,"remaining_time":0.06453064292},
{"learn":[3.293840636],"iteration":829,"passed_time":0.3135798099,"remaining_time":0.06422718998},
{"learn":[3.289279397],"iteration":830,"passed_time":0.3139602164,"remaining_time":0.06384991164},
{"learn":[3.286204979],"iteration":831,"passed_time":0.3142365007,"remaining_time":0.06345160111},
{"learn":[3.284833593],"iteration":832,"passed_time":0.31451391,"remaining_time":0.06305380909},
{"learn":[3.283519914],"iteration":833,"passed_time":0.3147385707,"remaining_time":0.06264580663},
{"learn":[3.282853026],"iteration":834,"passed_time":0.3151101858,"remaining_time":0.06226728222},
{"learn":[3.281944673],"iteration":835,"passed_time":0.3154148443,"remaining_time":0.06187563932},
{"learn":[3.279764865],"iteration":836,"passed_time":0.3157275443,"remaining_time":0.06148577028},
{"learn":[3.277468839],"iteration":837,"passed_time":0.3159702878,"remaining_time":0.06108256161},
{"learn":[3.277124974],"iteration":838,"passed_time":0.3163165703,"remaining_time":0.06069960407},
{"learn":[3.275636037],"iteration":839,"passed_time":0.3166124374,"remaining_time":0.06030713093},
{"learn":[3.274413635],"iteration":840,"passed_time":0.3171847138,"remaining_time":0.05996714566},
{"learn":[3.272636087],"iteration":841,"passed_time":0.3184383471,"remaining_time":0.05975446418},
{"learn":[3.269644466],"iteration":842,"passed_time":0.3191227038,"remaining_time":0.05943329122},
{"learn":[3.26852083],"iteration":843,"passed_time":0.3197143547,"remaining_time":0.05909412244},
{"learn":[3.267820927],"iteration":844,"passed_time":0.3202007168,"remaining_time":0.05873504272},
{"learn":[3.267331099],"iteration":845,"passed_time":0.3206128725,"remaining_time":0.05836215409},
{"learn":[3.267231014],"iteration":846,"passed_time":0.3211613578,"remaining_time":0.058013799},
{"learn":[3.267158695],"iteration":847,"passed_time":0.3215131401,"remaining_time":0.0576297138},
{"learn":[3.264718705],"iteration":848,"passed_time":0.3218515478,"remaining_time":0.05724332593},
{"learn":[3.261678512],"iteration":849,"passed_time":0.3221386235,"remaining_time":0.05684799238},
{"learn":[3.261368381],"iteration":850,"passed_time":0.3224140328,"remaining_time":0.05645087061},
{"learn":[3.260128799],"iteration":851,"passed_time":0.3227120249,"remaining_time":0.05605795737},
{"learn":[3.258972952],"iteration":852,"passed_time":0.3230536824,"remaining_time":0.05567279169},
{"learn":[3.258724846],"iteration":853,"passed_time":0.3233858819,"remaining_time":0.05528611096},
{"learn":[3.25686724],"iteration":854,"passed_time":0.3236610412,"remaining_time":0.05488988418},
{"learn":[3.255750259],"iteration":855,"passed_time":0.3239140761,"remaining_time":0.05449021842},
{"learn":[3.254915866],"iteration":856,"passed_time":0.3241910271,"remaining_time":0.0540948855},
{"learn":[3.254348625],"iteration":857,"passed_time":0.3245402261,"remaining_time":0.05371178568},
{"learn":[3.253408514],"iteration":858,"passed_time":0.3248310934,"remaining_time":0.05331918995},
{"learn":[3.253291714],"iteration":859,"passed_time":0.325069337,"remaining_time":0.05291826417},
{"learn":[3.250186342],"iteration":860,"passed_time":0.3253807037,"remaining_time":0.05252952128},
{"learn":[3.249141318],"iteration":861,"passed_time":0.3256341553,"remaining_time":0.05213168612},
{"learn":[3.246300388],"iteration":862,"passed_time":0.3259279391,"remaining_time":0.05174058825},
{"learn":[3.245205135],"iteration":863,"passed_time":0.3262041818,"remaining_time":0.05134695454},
{"learn":[3.244403535],"iteration":864,"passed_time":0.3265185067,"remaining_time":0.05095953573},
{"learn":[3.244211781],"iteration":865,"passed_time":0.3268789138,"remaining_time":0.05057941622},
{"learn":[3.242286347],"iteration":866,"passed_time":0.3271365319,"remaining_time":0.0501835741},
{"learn":[3.239606746],"iteration":867,"passed_time":0.3274917308,"remaining_time":0.04980288994},
{"learn":[3.236773361],"iteration":868,"passed_time":0.3277470573,"remaining_time":0.04940720887},
{"learn":[3.234552446],"iteration":869,"passed_time":0.3279943007,"remaining_time":0.04901064264},
{"learn":[3.233724647],"iteration":870,"passed_time":0.3283303751,"remaining_time":0.04862757565},
{"learn":[3.230851485],"iteration":871,"passed_time":0.328670991,"remaining_time":0.04824528309},
{"learn":[3.227728941],"iteration":872,"passed_time":0.3289430671,"remaining_time":0.04785311515},
{"learn":[3.225787575],"iteration":873,"passed_time":0.3292560588,"remaining_time":0.0474671206},
{"learn":[3.222797487],"iteration":874,"passed_time":0.3295059271,"remaining_time":0.0470722753},
{"learn":[3.22137014],"iteration":875,"passed_time":0.3297380043,"remaining_time":0.04667524261},
{"learn":[3.219701963],"iteration":876,"passed_time":0.3299727897,"remaining_time":0.04627896594},
{"learn":[3.21783327],"iteration":877,"passed_time":0.3303096974,"remaining_time":0.04589724724},
{"learn":[3.217713355],"iteration":878,"passed_time":0.3305596074,"remaining_time":0.04550365471},
{"learn":[3.217666091],"iteration":879,"passed_time":0.3308996817,"remaining_time":0.04512268386},
{"learn":[3.214962005],"iteration":880,"passed_time":0.3312077568,"remaining_time":0.04473748361},
{"learn":[3.214081828],"iteration":881,"passed_time":0.3314472504,"remaining_time":0.04434328293},
{"learn":[3.213358337],"iteration":882,"passed_time":0.3316808275,"remaining_time":0.04394864872},
{"learn":[3.210850401],"iteration":883,"passed_time":0.3321001497,"remaining_time":0.04357875267},
{"learn":[3.207810328],"iteration":884,"passed_time":0.3324751397,"remaining_time":0.04320298425},
{"learn":[3.204935073],"iteration":885,"passed_time":0.3327188415,"remaining_time":0.04281032498},
{"learn":[3.20280198],"iteration":886,"passed_time":0.3329719598,"remaining_time":0.04241920119},
{"learn":[3.200663495],"iteration":887,"passed_time":0.3331994954,"remaining_time":0.04202516158},
{"learn":[3.197301669],"iteration":888,"passed_time":0.333438989,"remaining_time":0.04163298963},
{"learn":[3.195666943],"iteration":889,"passed_time":0.3336882323,"remaining_time":0.04124236579},
{"learn":[3.193886506],"iteration":890,"passed_time":0.3339535586,"remaining_time":0.04085402681},
{"learn":[3.190601248],"iteration":891,"passed_time":0.3341949688,"remaining_time":0.04046306798},
{"learn":[3.188983797],"iteration":892,"passed_time":0.3344342958,"remaining_time":0.04007219446},
{"learn":[3.187365749],"iteration":893,"passed_time":0.3346995804,"remaining_time":0.03968473772},
{"learn":[3.186160771],"iteration":894,"passed_time":0.3349435322,"remaining_time":0.03929505127},
{"learn":[3.185358981],"iteration":895,"passed_time":0.3351835258,"remaining_time":0.03890523068},
{"learn":[3.183832164],"iteration":896,"passed_time":0.3354355608,"remaining_time":0.03851712682},
{"learn":[3.183106966],"iteration":897,"passed_time":0.3356809292,"remaining_time":0.0381285688},
{"learn":[3.182838152],"iteration":898,"passed_time":0.3359291726,"remaining_time":0.03774065232},
{"learn":[3.180835453],"iteration":899,"passed_time":0.3362550806,"remaining_time":0.03736167562},
{"learn":[3.179957348],"iteration":900,"passed_time":0.3365299899,"remaining_time":0.0369772131},
{"learn":[3.179752966],"iteration":901,"passed_time":0.3367933579,"remaining_time":0.03659173955},
{"learn":[3.178851983],"iteration":902,"passed_time":0.3370590592,"remaining_time":0.03620678709},
{"learn":[3.176748586],"iteration":903,"passed_time":0.3373260937,"remaining_time":0.03582224004},
{"learn":[3.172960988],"iteration":904,"passed_time":0.3375642957,"remaining_time":0.03543492607},
{"learn":[3.172794225],"iteration":905,"passed_time":0.3377972478,"remaining_time":0.03504739657},
{"learn":[3.169996507],"iteration":906,"passed_time":0.338039908,"remaining_time":0.03466120336},
{"learn":[3.16813015],"iteration":907,"passed_time":0.338403815,"remaining_time":0.03428761121},
{"learn":[3.166920871],"iteration":908,"passed_time":0.3386685996,"remaining_time":0.03390411723},
{"learn":[3.16531606],"iteration":909,"passed_time":0.3389036767,"remaining_time":0.03351794605},
{"learn":[3.162035247],"iteration":910,"passed_time":0.3392850832,"remaining_time":0.0331464022},
{"learn":[3.16189467],"iteration":911,"passed_time":0.3395502845,"remaining_time":0.03276362394},
{"learn":[3.161008416],"iteration":912,"passed_time":0.3398168607,"remaining_time":0.03238123426},
{"learn":[3.160560787],"iteration":913,"passed_time":0.3400481045,"remaining_time":0.03199577351},
{"learn":[3.160416261],"iteration":914,"passed_time":0.3402998895,"remaining_time":0.03161255804},
{"learn":[3.15844291],"iteration":915,"passed_time":0.3405360915,"remaining_time":0.03122820053},
{"learn":[3.155040501],"iteration":916,"passed_time":0.3407432527,"remaining_time":0.03084153759},
{"learn":[3.154937548],"iteration":917,"passed_time":0.3409901627,"remaining_time":0.03045881628},
{"learn":[3.153721161],"iteration":918,"passed_time":0.341205657,"remaining_time":0.03007362156},
{"learn":[3.153170511],"iteration":919,"passed_time":0.3414521921,"remaining_time":0.02969149497},
{"learn":[3.153113601],"iteration":920,"passed_time":0.3417404344,"remaining_time":0.0293132403},
{"learn":[3.150607379],"iteration":921,"passed_time":0.3420076773,"remaining_time":0.02893340437},
{"learn":[3.148408359],"iteration":922,"passed_time":0.3422710869,"remaining_time":0.02855349263},
{"learn":[3.147495728],"iteration":923,"passed_time":0.3425217469,"remaining_time":0.02817278438},
{"learn":[3.146946235],"iteration":924,"passed_time":0.3427772818,"remaining_time":0.02779275258},
{"learn":[3.14472738],"iteration":925,"passed_time":0.3431410638,"remaining_time":0.02742164008},
{"learn":[3.144469477],"iteration":926,"passed_time":0.3434096816,"remaining_time":0.02704304936},
{"learn":[3.142975516],"iteration":927,"passed_time":0.3436955073,"remaining_time":0.02666603074},
{"learn":[3.14079113],"iteration":928,"passed_time":0.3439372509,"remaining_time":0.02628583941},
{"learn":[3.138173032],"iteration":929,"passed_time":0.3442017022,"remaining_time":0.025907655},
{"learn":[3.136352813],"iteration":930,"passed_time":0.3445008192,"remaining_time":0.02553228413},
{"learn":[3.133735004],"iteration":931,"passed_time":0.3447970196,"remaining_time":0.02515686409},
{"learn":[3.1319496],"iteration":932,"passed_time":0.3450935951,"remaining_time":0.0247816408},
{"learn":[3.129865343],"iteration":933,"passed_time":0.3453898788,"remaining_time":0.02440656531},
{"learn":[3.129830206],"iteration":934,"passed_time":0.3455838737,"remaining_time":0.02402454737},
{"learn":[3.126676562],"iteration":935,"passed_time":0.3458607829,"remaining_time":0.02364860054},
{"learn":[3.12645665],"iteration":936,"passed_time":0.3462429394,"remaining_time":0.0232799415},
{"learn":[3.126378007],"iteration":937,"passed_time":0.3465307234,"remaining_time":0.02290501583},
{"learn":[3.124621914],"iteration":938,"passed_time":0.346798133,"remaining_time":0.02252895219},
{"learn":[3.123379018],"iteration":939,"passed_time":0.3471418321,"remaining_time":0.02215798929},
{"learn":[3.123332451],"iteration":940,"passed_time":0.3475050308,"remaining_time":0.02178830693},
{"learn":[3.122432444],"iteration":941,"passed_time":0.3477549408,"remaining_time":0.02141166302},
{"learn":[3.121889006],"iteration":942,"passed_time":0.3480078091,"remaining_time":0.02103546672},
{"learn":[3.121070914],"iteration":943,"passed_time":0.3482370946,"remaining_time":0.02065813273},
{"learn":[3.118444705],"iteration":944,"passed_time":0.3484682968,"remaining_time":0.02028122362},
{"learn":[3.116820458],"iteration":945,"passed_time":0.3487016239,"remaining_time":0.01990474386},
{"learn":[3.114971041],"iteration":946,"passed_time":0.3490009909,"remaining_time":0.01953226243},
{"learn":[3.114685138],"iteration":947,"passed_time":0.3492544008,"remaining_time":0.01915741439},
{"learn":[3.113399363],"iteration":948,"passed_time":0.3495099357,"remaining_time":0.01878293648},
{"learn":[3.110575399],"iteration":949,"passed_time":0.3497938448,"remaining_time":0.01841020236},
{"learn":[3.110466553],"iteration":950,"passed_time":0.3500335884,"remaining_time":0.01803537942},
{"learn":[3.108691641],"iteration":951,"passed_time":0.3502958731,"remaining_time":0.01766197679},
{"learn":[3.107898017],"iteration":952,"passed_time":0.3505585744,"remaining_time":0.01728882791},
{"learn":[3.105551729],"iteration":953,"passed_time":0.3509466474,"remaining_time":0.01692195575},
{"learn":[3.104824945],"iteration":954,"passed_time":0.351212932,"remaining_time":0.01654930046},
{"learn":[3.103186704],"iteration":955,"passed_time":0.3514878413,"remaining_time":0.01617726466},
{"learn":[3.102330655],"iteration":956,"passed_time":0.3518592898,"remaining_time":0.01580976955},
{"learn":[3.102291298],"iteration":957,"passed_time":0.3521634066,"remaining_time":0.01543931428},
{"learn":[3.100363529],"iteration":958,"passed_time":0.3524706068,"remaining_time":0.01506912917},
{"learn":[3.097871596],"iteration":959,"passed_time":0.3528930122,"remaining_time":0.01470387551},
{"learn":[3.097372213],"iteration":960,"passed_time":0.3531417556,"remaining_time":0.01433145522},
{"learn":[3.095981813],"iteration":961,"passed_time":0.3533955405,"remaining_time":0.0139594912},
{"learn":[3.095347452],"iteration":962,"passed_time":0.3536861161,"remaining_time":0.01358918618},
{"learn":[3.094728409],"iteration":963,"passed_time":0.353925068,"remaining_time":0.01321711872},
{"learn":[3.094118537],"iteration":964,"passed_time":0.3541813945,"remaining_time":0.01284595731},
{"learn":[3.093793695],"iteration":965,"passed_time":0.3544425542,"remaining_time":0.01247520377},
{"learn":[3.092581602],"iteration":966,"passed_time":0.3547652123,"remaining_time":0.0121067756},
{"learn":[3.091694202],"iteration":967,"passed_time":0.3551896177,"remaining_time":0.01174180554},
{"learn":[3.090298312],"iteration":968,"passed_time":0.3554695685,"remaining_time":0.01137209146},
{"learn":[3.090020107],"iteration":969,"passed_time":0.3556981458,"remaining_time":0.01100097358},
{"learn":[3.088949869],"iteration":970,"passed_time":0.3559281813,"remaining_time":0.01063019285},
{"learn":[3.086700204],"iteration":971,"passed_time":0.3562524227,"remaining_time":0.01026241547},
{"learn":[3.086584317],"iteration":972,"passed_time":0.3564953745,"remaining_time":0.009892471853},
{"learn":[3.084850742],"iteration":973,"passed_time":0.3567390764,"remaining_time":0.00952280902},
{"learn":[3.084239948],"iteration":974,"passed_time":0.3569739451,"remaining_time":0.00915317808},
{"learn":[3.082561673],"iteration":975,"passed_time":0.357217272,"remaining_time":0.008784031278},
{"learn":[3.07991814],"iteration":976,"passed_time":0.3574585989,"remaining_time":0.008415094958},
{"learn":[3.079350277],"iteration":977,"passed_time":0.3577188836,"remaining_time":0.008046846052},
{"learn":[3.077637462],"iteration":978,"passed_time":0.3580390001,"remaining_time":0.007680101125},
{"learn":[3.076733301],"iteration":979,"passed_time":0.3582887434,"remaining_time":0.007312015172},
{"learn":[3.07594065],"iteration":980,"passed_time":0.3586125681,"remaining_time":0.006945605295},
{"learn":[3.072594655],"iteration":981,"passed_time":0.3589408927,"remaining_time":0.006579364632},
{"learn":[3.071977674],"iteration":982,"passed_time":0.3592125521,"remaining_time":0.006212221146},
{"learn":[3.069532634],"iteration":983,"passed_time":0.3594605872,"remaining_time":0.005844887596},
{"learn":[3.068870784],"iteration":984,"passed_time":0.3597126638,"remaining_time":0.005477857824},
{"learn":[3.068801463],"iteration":985,"passed_time":0.3599697403,"remaining_time":0.005111132215},
{"learn":[3.067433249],"iteration":986,"passed_time":0.3602762321,"remaining_time":0.004745279653},
{"learn":[3.065611456],"iteration":987,"passed_time":0.3605019761,"remaining_time":0.004378566511},
{"learn":[3.063039162],"iteration":988,"passed_time":0.3607845102,"remaining_time":0.004012770083},
{"learn":[3.06177873],"iteration":989,"passed_time":0.3610331286,"remaining_time":0.003646799279},
{"learn":[3.061689148],"iteration":990,"passed_time":0.3612576643,"remaining_time":0.003280846598},
{"learn":[3.058984039],"iteration":991,"passed_time":0.3615045327,"remaining_time":0.002915359135},
{"learn":[3.057492984],"iteration":992,"passed_time":0.3617765671,"remaining_time":0.002550287986},
{"learn":[3.057290731],"iteration":993,"passed_time":0.3620111025,"remaining_time":0.002185177681},
{"learn":[3.056068348],"iteration":994,"passed_time":0.3622619709,"remaining_time":0.001820411914},
{"learn":[3.054987307],"iteration":995,"passed_time":0.362530422,"remaining_time":0.00145594547},
{"learn":[3.054200234],"iteration":996,"passed_time":0.3628581216,"remaining_time":0.001091849915},
{"learn":[3.052732869],"iteration":997,"passed_time":0.3631081983,"remaining_time":0.0007276717401},
{"learn":[3.051787862],"iteration":998,"passed_time":0.3633317757,"remaining_time":0.0003636954712},
{"learn":[3.051366222],"iteration":999,"passed_time":0.3635839773,"remaining_time":0}
]}